{
  "displayName": "Mata-Utu, Uvea, Wallis and Futuna",
  "thresholds": {
    "heat_celsius": 28.0,
    "muggy_celsius": 27.9
  },
  "histYearly": {
    "1940": {
      "heat": 2,
      "muggy": 3,
      "rain": 17,
      "snow": 0,
      "mosquito": 269,
      "dry": 3,
      "heat_roll5": 2.0,
      "muggy_roll5": 3.0,
      "rain_roll5": 17.0,
      "snow_roll5": 0.0,
      "mosquito_roll5": 269.0,
      "dry_roll5": 3.0,
      "heat_roll10": 2.0,
      "muggy_roll10": 3.0,
      "rain_roll10": 17.0,
      "snow_roll10": 0.0,
      "mosquito_roll10": 269.0,
      "dry_roll10": 3.0,
      "springFrost": 0,
      "fallFrost": 0
    },
    "1941": {
      "heat": 9,
      "muggy": 9,
      "rain": 27,
      "snow": 0,
      "mosquito": 349,
      "dry": 8,
      "heat_roll5": 5.5,
      "muggy_roll5": 6.0,
      "rain_roll5": 22.0,
      "snow_roll5": 0.0,
      "mosquito_roll5": 309.0,
      "dry_roll5": 5.5,
      "heat_roll10": 5.5,
      "muggy_roll10": 6.0,
      "rain_roll10": 22.0,
      "snow_roll10": 0.0,
      "mosquito_roll10": 309.0,
      "dry_roll10": 5.5,
      "springFrost": 0,
      "fallFrost": 0
    },
    "1942": {
      "heat": 3,
      "muggy": 3,
      "rain": 16,
      "snow": 0,
      "mosquito": 347,
      "dry": 7,
      "heat_roll5": 4.7,
      "muggy_roll5": 5.0,
      "rain_roll5": 20.0,
      "snow_roll5": 0.0,
      "mosquito_roll5": 321.7,
      "dry_roll5": 6.0,
      "heat_roll10": 4.7,
      "muggy_roll10": 5.0,
      "rain_roll10": 20.0,
      "snow_roll10": 0.0,
      "mosquito_roll10": 321.7,
      "dry_roll10": 6.0,
      "springFrost": 0,
      "fallFrost": 0
    },
    "1943": {
      "heat": 0,
      "muggy": 0,
      "rain": 16,
      "snow": 0,
      "mosquito": 334,
      "dry": 9,
      "heat_roll5": 3.5,
      "muggy_roll5": 3.8,
      "rain_roll5": 19.0,
      "snow_roll5": 0.0,
      "mosquito_roll5": 324.8,
      "dry_roll5": 6.8,
      "heat_roll10": 3.5,
      "muggy_roll10": 3.8,
      "rain_roll10": 19.0,
      "snow_roll10": 0.0,
      "mosquito_roll10": 324.8,
      "dry_roll10": 6.8,
      "springFrost": 0,
      "fallFrost": 0
    },
    "1944": {
      "heat": 1,
      "muggy": 2,
      "rain": 22,
      "snow": 0,
      "mosquito": 361,
      "dry": 4,
      "heat_roll5": 3.0,
      "muggy_roll5": 3.4,
      "rain_roll5": 19.6,
      "snow_roll5": 0.0,
      "mosquito_roll5": 332.0,
      "dry_roll5": 6.2,
      "heat_roll10": 3.0,
      "muggy_roll10": 3.4,
      "rain_roll10": 19.6,
      "snow_roll10": 0.0,
      "mosquito_roll10": 332.0,
      "dry_roll10": 6.2,
      "springFrost": 0,
      "fallFrost": 0
    },
    "1945": {
      "heat": 1,
      "muggy": 1,
      "rain": 7,
      "snow": 0,
      "mosquito": 360,
      "dry": 5,
      "heat_roll5": 2.8,
      "muggy_roll5": 3.0,
      "rain_roll5": 17.6,
      "snow_roll5": 0.0,
      "mosquito_roll5": 350.2,
      "dry_roll5": 6.6,
      "heat_roll10": 2.7,
      "muggy_roll10": 3.0,
      "rain_roll10": 17.5,
      "snow_roll10": 0.0,
      "mosquito_roll10": 336.7,
      "dry_roll10": 6.0,
      "springFrost": 0,
      "fallFrost": 0
    },
    "1946": {
      "heat": 0,
      "muggy": 0,
      "rain": 20,
      "snow": 0,
      "mosquito": 343,
      "dry": 9,
      "heat_roll5": 1.0,
      "muggy_roll5": 1.2,
      "rain_roll5": 16.2,
      "snow_roll5": 0.0,
      "mosquito_roll5": 349.0,
      "dry_roll5": 6.8,
      "heat_roll10": 2.3,
      "muggy_roll10": 2.6,
      "rain_roll10": 17.9,
      "snow_roll10": 0.0,
      "mosquito_roll10": 337.6,
      "dry_roll10": 6.4,
      "springFrost": 0,
      "fallFrost": 0
    },
    "1947": {
      "heat": 5,
      "muggy": 5,
      "rain": 7,
      "snow": 0,
      "mosquito": 357,
      "dry": 5,
      "heat_roll5": 1.4,
      "muggy_roll5": 1.6,
      "rain_roll5": 14.4,
      "snow_roll5": 0.0,
      "mosquito_roll5": 351.0,
      "dry_roll5": 6.4,
      "heat_roll10": 2.6,
      "muggy_roll10": 2.9,
      "rain_roll10": 16.5,
      "snow_roll10": 0.0,
      "mosquito_roll10": 340.0,
      "dry_roll10": 6.2,
      "springFrost": 0,
      "fallFrost": 0
    },
    "1948": {
      "heat": 0,
      "muggy": 0,
      "rain": 33,
      "snow": 0,
      "mosquito": 360,
      "dry": 7,
      "heat_roll5": 1.4,
      "muggy_roll5": 1.6,
      "rain_roll5": 17.8,
      "snow_roll5": 0.0,
      "mosquito_roll5": 356.2,
      "dry_roll5": 6.0,
      "heat_roll10": 2.3,
      "muggy_roll10": 2.6,
      "rain_roll10": 18.3,
      "snow_roll10": 0.0,
      "mosquito_roll10": 342.2,
      "dry_roll10": 6.3,
      "springFrost": 0,
      "fallFrost": 0
    },
    "1949": {
      "heat": 6,
      "muggy": 9,
      "rain": 6,
      "snow": 0,
      "mosquito": 359,
      "dry": 6,
      "heat_roll5": 2.4,
      "muggy_roll5": 3.0,
      "rain_roll5": 14.6,
      "snow_roll5": 0.0,
      "mosquito_roll5": 355.8,
      "dry_roll5": 6.4,
      "heat_roll10": 2.7,
      "muggy_roll10": 3.2,
      "rain_roll10": 17.1,
      "snow_roll10": 0.0,
      "mosquito_roll10": 343.9,
      "dry_roll10": 6.3,
      "springFrost": 0,
      "fallFrost": 0
    },
    "1950": {
      "heat": 2,
      "muggy": 1,
      "rain": 8,
      "snow": 0,
      "mosquito": 352,
      "dry": 4,
      "heat_roll5": 2.6,
      "muggy_roll5": 3.0,
      "rain_roll5": 14.8,
      "snow_roll5": 0.0,
      "mosquito_roll5": 354.2,
      "dry_roll5": 6.2,
      "heat_roll10": 2.7,
      "muggy_roll10": 3.0,
      "rain_roll10": 16.2,
      "snow_roll10": 0.0,
      "mosquito_roll10": 352.2,
      "dry_roll10": 6.4,
      "springFrost": 0,
      "fallFrost": 0
    },
    "1951": {
      "heat": 2,
      "muggy": 2,
      "rain": 30,
      "snow": 0,
      "mosquito": 330,
      "dry": 14,
      "heat_roll5": 3.0,
      "muggy_roll5": 3.4,
      "rain_roll5": 16.8,
      "snow_roll5": 0.0,
      "mosquito_roll5": 351.6,
      "dry_roll5": 7.2,
      "heat_roll10": 2.0,
      "muggy_roll10": 2.3,
      "rain_roll10": 16.5,
      "snow_roll10": 0.0,
      "mosquito_roll10": 350.3,
      "dry_roll10": 7.0,
      "springFrost": 0,
      "fallFrost": 0
    },
    "1952": {
      "heat": 18,
      "muggy": 19,
      "rain": 31,
      "snow": 0,
      "mosquito": 358,
      "dry": 5,
      "heat_roll5": 5.6,
      "muggy_roll5": 6.2,
      "rain_roll5": 21.6,
      "snow_roll5": 0.0,
      "mosquito_roll5": 351.8,
      "dry_roll5": 7.2,
      "heat_roll10": 3.5,
      "muggy_roll10": 3.9,
      "rain_roll10": 18.0,
      "snow_roll10": 0.0,
      "mosquito_roll10": 351.4,
      "dry_roll10": 6.8,
      "springFrost": 0,
      "fallFrost": 0
    },
    "1953": {
      "heat": 3,
      "muggy": 4,
      "rain": 14,
      "snow": 0,
      "mosquito": 343,
      "dry": 6,
      "heat_roll5": 6.2,
      "muggy_roll5": 7.0,
      "rain_roll5": 17.8,
      "snow_roll5": 0.0,
      "mosquito_roll5": 348.4,
      "dry_roll5": 7.0,
      "heat_roll10": 3.8,
      "muggy_roll10": 4.3,
      "rain_roll10": 17.8,
      "snow_roll10": 0.0,
      "mosquito_roll10": 352.3,
      "dry_roll10": 6.5,
      "springFrost": 0,
      "fallFrost": 0
    },
    "1954": {
      "heat": 1,
      "muggy": 2,
      "rain": 23,
      "snow": 0,
      "mosquito": 353,
      "dry": 5,
      "heat_roll5": 5.2,
      "muggy_roll5": 5.6,
      "rain_roll5": 21.2,
      "snow_roll5": 0.0,
      "mosquito_roll5": 347.2,
      "dry_roll5": 6.8,
      "heat_roll10": 3.8,
      "muggy_roll10": 4.3,
      "rain_roll10": 17.9,
      "snow_roll10": 0.0,
      "mosquito_roll10": 351.5,
      "dry_roll10": 6.6,
      "springFrost": 0,
      "fallFrost": 0
    },
    "1955": {
      "heat": 1,
      "muggy": 1,
      "rain": 28,
      "snow": 0,
      "mosquito": 354,
      "dry": 9,
      "heat_roll5": 5.0,
      "muggy_roll5": 5.6,
      "rain_roll5": 25.2,
      "snow_roll5": 0.0,
      "mosquito_roll5": 347.6,
      "dry_roll5": 7.8,
      "heat_roll10": 3.8,
      "muggy_roll10": 4.3,
      "rain_roll10": 20.0,
      "snow_roll10": 0.0,
      "mosquito_roll10": 350.9,
      "dry_roll10": 7.0,
      "springFrost": 0,
      "fallFrost": 0
    },
    "1956": {
      "heat": 1,
      "muggy": 2,
      "rain": 14,
      "snow": 0,
      "mosquito": 354,
      "dry": 6,
      "heat_roll5": 4.8,
      "muggy_roll5": 5.6,
      "rain_roll5": 22.0,
      "snow_roll5": 0.0,
      "mosquito_roll5": 352.4,
      "dry_roll5": 6.2,
      "heat_roll10": 3.9,
      "muggy_roll10": 4.5,
      "rain_roll10": 19.4,
      "snow_roll10": 0.0,
      "mosquito_roll10": 352.0,
      "dry_roll10": 6.7,
      "springFrost": 0,
      "fallFrost": 0
    },
    "1957": {
      "heat": 8,
      "muggy": 8,
      "rain": 22,
      "snow": 0,
      "mosquito": 327,
      "dry": 12,
      "heat_roll5": 2.8,
      "muggy_roll5": 3.4,
      "rain_roll5": 20.2,
      "snow_roll5": 0.0,
      "mosquito_roll5": 346.2,
      "dry_roll5": 7.6,
      "heat_roll10": 4.2,
      "muggy_roll10": 4.8,
      "rain_roll10": 20.9,
      "snow_roll10": 0.0,
      "mosquito_roll10": 349.0,
      "dry_roll10": 7.4,
      "springFrost": 0,
      "fallFrost": 0
    },
    "1958": {
      "heat": 7,
      "muggy": 9,
      "rain": 20,
      "snow": 0,
      "mosquito": 346,
      "dry": 5,
      "heat_roll5": 3.6,
      "muggy_roll5": 4.4,
      "rain_roll5": 21.4,
      "snow_roll5": 0.0,
      "mosquito_roll5": 346.8,
      "dry_roll5": 7.4,
      "heat_roll10": 4.9,
      "muggy_roll10": 5.7,
      "rain_roll10": 19.6,
      "snow_roll10": 0.0,
      "mosquito_roll10": 347.6,
      "dry_roll10": 7.2,
      "springFrost": 0,
      "fallFrost": 0
    },
    "1959": {
      "heat": 10,
      "muggy": 10,
      "rain": 34,
      "snow": 0,
      "mosquito": 354,
      "dry": 5,
      "heat_roll5": 5.4,
      "muggy_roll5": 6.0,
      "rain_roll5": 23.6,
      "snow_roll5": 0.0,
      "mosquito_roll5": 347.0,
      "dry_roll5": 7.4,
      "heat_roll10": 5.3,
      "muggy_roll10": 5.8,
      "rain_roll10": 22.4,
      "snow_roll10": 0.0,
      "mosquito_roll10": 347.1,
      "dry_roll10": 7.1,
      "springFrost": 0,
      "fallFrost": 0
    },
    "1960": {
      "heat": 0,
      "muggy": 2,
      "rain": 15,
      "snow": 0,
      "mosquito": 357,
      "dry": 5,
      "heat_roll5": 5.2,
      "muggy_roll5": 6.2,
      "rain_roll5": 21.0,
      "snow_roll5": 0.0,
      "mosquito_roll5": 347.6,
      "dry_roll5": 6.6,
      "heat_roll10": 5.1,
      "muggy_roll10": 5.9,
      "rain_roll10": 23.1,
      "snow_roll10": 0.0,
      "mosquito_roll10": 347.6,
      "dry_roll10": 7.2,
      "springFrost": 0,
      "fallFrost": 0
    },
    "1961": {
      "heat": 8,
      "muggy": 10,
      "rain": 14,
      "snow": 0,
      "mosquito": 354,
      "dry": 5,
      "heat_roll5": 6.6,
      "muggy_roll5": 7.8,
      "rain_roll5": 21.0,
      "snow_roll5": 0.0,
      "mosquito_roll5": 347.6,
      "dry_roll5": 6.4,
      "heat_roll10": 5.7,
      "muggy_roll10": 6.7,
      "rain_roll10": 21.5,
      "snow_roll10": 0.0,
      "mosquito_roll10": 350.0,
      "dry_roll10": 6.3,
      "springFrost": 0,
      "fallFrost": 0
    },
    "1962": {
      "heat": 4,
      "muggy": 5,
      "rain": 15,
      "snow": 0,
      "mosquito": 356,
      "dry": 6,
      "heat_roll5": 5.8,
      "muggy_roll5": 7.2,
      "rain_roll5": 19.6,
      "snow_roll5": 0.0,
      "mosquito_roll5": 353.4,
      "dry_roll5": 5.2,
      "heat_roll10": 4.3,
      "muggy_roll10": 5.3,
      "rain_roll10": 19.9,
      "snow_roll10": 0.0,
      "mosquito_roll10": 349.8,
      "dry_roll10": 6.4,
      "springFrost": 0,
      "fallFrost": 0
    },
    "1963": {
      "heat": 7,
      "muggy": 7,
      "rain": 10,
      "snow": 0,
      "mosquito": 358,
      "dry": 4,
      "heat_roll5": 5.8,
      "muggy_roll5": 6.8,
      "rain_roll5": 17.6,
      "snow_roll5": 0.0,
      "mosquito_roll5": 355.8,
      "dry_roll5": 5.0,
      "heat_roll10": 4.7,
      "muggy_roll10": 5.6,
      "rain_roll10": 19.5,
      "snow_roll10": 0.0,
      "mosquito_roll10": 351.3,
      "dry_roll10": 6.2,
      "springFrost": 0,
      "fallFrost": 0
    },
    "1964": {
      "heat": 17,
      "muggy": 17,
      "rain": 17,
      "snow": 0,
      "mosquito": 353,
      "dry": 8,
      "heat_roll5": 7.2,
      "muggy_roll5": 8.2,
      "rain_roll5": 14.2,
      "snow_roll5": 0.0,
      "mosquito_roll5": 355.6,
      "dry_roll5": 5.6,
      "heat_roll10": 6.3,
      "muggy_roll10": 7.1,
      "rain_roll10": 18.9,
      "snow_roll10": 0.0,
      "mosquito_roll10": 351.3,
      "dry_roll10": 6.5,
      "springFrost": 0,
      "fallFrost": 0
    },
    "1965": {
      "heat": 4,
      "muggy": 5,
      "rain": 18,
      "snow": 0,
      "mosquito": 348,
      "dry": 9,
      "heat_roll5": 8.0,
      "muggy_roll5": 8.8,
      "rain_roll5": 14.8,
      "snow_roll5": 0.0,
      "mosquito_roll5": 353.8,
      "dry_roll5": 6.4,
      "heat_roll10": 6.6,
      "muggy_roll10": 7.5,
      "rain_roll10": 17.9,
      "snow_roll10": 0.0,
      "mosquito_roll10": 350.7,
      "dry_roll10": 6.5,
      "springFrost": 0,
      "fallFrost": 0
    },
    "1966": {
      "heat": 14,
      "muggy": 15,
      "rain": 20,
      "snow": 0,
      "mosquito": 348,
      "dry": 4,
      "heat_roll5": 9.2,
      "muggy_roll5": 9.8,
      "rain_roll5": 16.0,
      "snow_roll5": 0.0,
      "mosquito_roll5": 352.6,
      "dry_roll5": 6.2,
      "heat_roll10": 7.9,
      "muggy_roll10": 8.8,
      "rain_roll10": 18.5,
      "snow_roll10": 0.0,
      "mosquito_roll10": 350.1,
      "dry_roll10": 6.3,
      "springFrost": 0,
      "fallFrost": 0
    },
    "1967": {
      "heat": 3,
      "muggy": 3,
      "rain": 23,
      "snow": 0,
      "mosquito": 357,
      "dry": 4,
      "heat_roll5": 9.0,
      "muggy_roll5": 9.4,
      "rain_roll5": 17.6,
      "snow_roll5": 0.0,
      "mosquito_roll5": 352.8,
      "dry_roll5": 5.8,
      "heat_roll10": 7.4,
      "muggy_roll10": 8.3,
      "rain_roll10": 18.6,
      "snow_roll10": 0.0,
      "mosquito_roll10": 353.1,
      "dry_roll10": 5.5,
      "springFrost": 0,
      "fallFrost": 0
    },
    "1968": {
      "heat": 16,
      "muggy": 19,
      "rain": 31,
      "snow": 0,
      "mosquito": 352,
      "dry": 7,
      "heat_roll5": 10.8,
      "muggy_roll5": 11.8,
      "rain_roll5": 21.8,
      "snow_roll5": 0.0,
      "mosquito_roll5": 351.6,
      "dry_roll5": 6.4,
      "heat_roll10": 8.3,
      "muggy_roll10": 9.3,
      "rain_roll10": 19.7,
      "snow_roll10": 0.0,
      "mosquito_roll10": 353.7,
      "dry_roll10": 5.7,
      "springFrost": 0,
      "fallFrost": 0
    },
    "1969": {
      "heat": 22,
      "muggy": 21,
      "rain": 19,
      "snow": 0,
      "mosquito": 345,
      "dry": 7,
      "heat_roll5": 11.8,
      "muggy_roll5": 12.6,
      "rain_roll5": 22.2,
      "snow_roll5": 0.0,
      "mosquito_roll5": 350.0,
      "dry_roll5": 6.2,
      "heat_roll10": 9.5,
      "muggy_roll10": 10.4,
      "rain_roll10": 18.2,
      "snow_roll10": 0.0,
      "mosquito_roll10": 352.8,
      "dry_roll10": 5.9,
      "springFrost": 0,
      "fallFrost": 0
    },
    "1970": {
      "heat": 14,
      "muggy": 13,
      "rain": 21,
      "snow": 0,
      "mosquito": 350,
      "dry": 7,
      "heat_roll5": 13.8,
      "muggy_roll5": 14.2,
      "rain_roll5": 22.8,
      "snow_roll5": 0.0,
      "mosquito_roll5": 350.4,
      "dry_roll5": 5.8,
      "heat_roll10": 10.9,
      "muggy_roll10": 11.5,
      "rain_roll10": 18.8,
      "snow_roll10": 0.0,
      "mosquito_roll10": 352.1,
      "dry_roll10": 6.1,
      "springFrost": 0,
      "fallFrost": 0
    },
    "1971": {
      "heat": 2,
      "muggy": 2,
      "rain": 10,
      "snow": 0,
      "mosquito": 351,
      "dry": 7,
      "heat_roll5": 11.4,
      "muggy_roll5": 11.6,
      "rain_roll5": 20.8,
      "snow_roll5": 0.0,
      "mosquito_roll5": 351.0,
      "dry_roll5": 6.4,
      "heat_roll10": 10.3,
      "muggy_roll10": 10.7,
      "rain_roll10": 18.4,
      "snow_roll10": 0.0,
      "mosquito_roll10": 351.8,
      "dry_roll10": 6.3,
      "springFrost": 0,
      "fallFrost": 0
    },
    "1972": {
      "heat": 8,
      "muggy": 9,
      "rain": 26,
      "snow": 0,
      "mosquito": 356,
      "dry": 6,
      "heat_roll5": 12.4,
      "muggy_roll5": 12.8,
      "rain_roll5": 21.4,
      "snow_roll5": 0.0,
      "mosquito_roll5": 350.8,
      "dry_roll5": 6.8,
      "heat_roll10": 10.7,
      "muggy_roll10": 11.1,
      "rain_roll10": 19.5,
      "snow_roll10": 0.0,
      "mosquito_roll10": 351.8,
      "dry_roll10": 6.3,
      "springFrost": 0,
      "fallFrost": 0
    },
    "1973": {
      "heat": 15,
      "muggy": 17,
      "rain": 15,
      "snow": 0,
      "mosquito": 360,
      "dry": 3,
      "heat_roll5": 12.2,
      "muggy_roll5": 12.4,
      "rain_roll5": 18.2,
      "snow_roll5": 0.0,
      "mosquito_roll5": 352.4,
      "dry_roll5": 6.0,
      "heat_roll10": 11.5,
      "muggy_roll10": 12.1,
      "rain_roll10": 20.0,
      "snow_roll10": 0.0,
      "mosquito_roll10": 352.0,
      "dry_roll10": 6.2,
      "springFrost": 0,
      "fallFrost": 0
    },
    "1974": {
      "heat": 1,
      "muggy": 2,
      "rain": 21,
      "snow": 0,
      "mosquito": 342,
      "dry": 10,
      "heat_roll5": 8.0,
      "muggy_roll5": 8.6,
      "rain_roll5": 18.6,
      "snow_roll5": 0.0,
      "mosquito_roll5": 351.8,
      "dry_roll5": 6.6,
      "heat_roll10": 9.9,
      "muggy_roll10": 10.6,
      "rain_roll10": 20.4,
      "snow_roll10": 0.0,
      "mosquito_roll10": 350.9,
      "dry_roll10": 6.4,
      "springFrost": 0,
      "fallFrost": 0
    },
    "1975": {
      "heat": 0,
      "muggy": 0,
      "rain": 9,
      "snow": 0,
      "mosquito": 358,
      "dry": 4,
      "heat_roll5": 5.2,
      "muggy_roll5": 6.0,
      "rain_roll5": 16.2,
      "snow_roll5": 0.0,
      "mosquito_roll5": 353.4,
      "dry_roll5": 6.0,
      "heat_roll10": 9.5,
      "muggy_roll10": 10.1,
      "rain_roll10": 19.5,
      "snow_roll10": 0.0,
      "mosquito_roll10": 351.9,
      "dry_roll10": 5.9,
      "springFrost": 0,
      "fallFrost": 0
    },
    "1976": {
      "heat": 0,
      "muggy": 1,
      "rain": 8,
      "snow": 0,
      "mosquito": 345,
      "dry": 8,
      "heat_roll5": 4.8,
      "muggy_roll5": 5.8,
      "rain_roll5": 15.8,
      "snow_roll5": 0.0,
      "mosquito_roll5": 352.2,
      "dry_roll5": 6.2,
      "heat_roll10": 8.1,
      "muggy_roll10": 8.7,
      "rain_roll10": 18.3,
      "snow_roll10": 0.0,
      "mosquito_roll10": 351.6,
      "dry_roll10": 6.3,
      "springFrost": 0,
      "fallFrost": 0
    },
    "1977": {
      "heat": 7,
      "muggy": 7,
      "rain": 13,
      "snow": 0,
      "mosquito": 329,
      "dry": 9,
      "heat_roll5": 4.6,
      "muggy_roll5": 5.4,
      "rain_roll5": 13.2,
      "snow_roll5": 0.0,
      "mosquito_roll5": 346.8,
      "dry_roll5": 6.8,
      "heat_roll10": 8.5,
      "muggy_roll10": 9.1,
      "rain_roll10": 17.3,
      "snow_roll10": 0.0,
      "mosquito_roll10": 348.8,
      "dry_roll10": 6.8,
      "springFrost": 0,
      "fallFrost": 0
    },
    "1978": {
      "heat": 6,
      "muggy": 6,
      "rain": 35,
      "snow": 0,
      "mosquito": 347,
      "dry": 7,
      "heat_roll5": 2.8,
      "muggy_roll5": 3.2,
      "rain_roll5": 17.2,
      "snow_roll5": 0.0,
      "mosquito_roll5": 344.2,
      "dry_roll5": 7.6,
      "heat_roll10": 7.5,
      "muggy_roll10": 7.8,
      "rain_roll10": 17.7,
      "snow_roll10": 0.0,
      "mosquito_roll10": 348.3,
      "dry_roll10": 6.8,
      "springFrost": 0,
      "fallFrost": 0
    },
    "1979": {
      "heat": 14,
      "muggy": 13,
      "rain": 15,
      "snow": 0,
      "mosquito": 337,
      "dry": 10,
      "heat_roll5": 5.4,
      "muggy_roll5": 5.4,
      "rain_roll5": 16.0,
      "snow_roll5": 0.0,
      "mosquito_roll5": 343.2,
      "dry_roll5": 7.6,
      "heat_roll10": 6.7,
      "muggy_roll10": 7.0,
      "rain_roll10": 17.3,
      "snow_roll10": 0.0,
      "mosquito_roll10": 347.5,
      "dry_roll10": 7.1,
      "springFrost": 0,
      "fallFrost": 0
    },
    "1980": {
      "heat": 11,
      "muggy": 11,
      "rain": 8,
      "snow": 0,
      "mosquito": 354,
      "dry": 5,
      "heat_roll5": 7.6,
      "muggy_roll5": 7.6,
      "rain_roll5": 15.8,
      "snow_roll5": 0.0,
      "mosquito_roll5": 342.4,
      "dry_roll5": 7.8,
      "heat_roll10": 6.4,
      "muggy_roll10": 6.8,
      "rain_roll10": 16.0,
      "snow_roll10": 0.0,
      "mosquito_roll10": 347.9,
      "dry_roll10": 6.9,
      "springFrost": 0,
      "fallFrost": 0
    },
    "1981": {
      "heat": 5,
      "muggy": 5,
      "rain": 17,
      "snow": 0,
      "mosquito": 355,
      "dry": 5,
      "heat_roll5": 8.6,
      "muggy_roll5": 8.4,
      "rain_roll5": 17.6,
      "snow_roll5": 0.0,
      "mosquito_roll5": 344.4,
      "dry_roll5": 7.2,
      "heat_roll10": 6.7,
      "muggy_roll10": 7.1,
      "rain_roll10": 16.7,
      "snow_roll10": 0.0,
      "mosquito_roll10": 348.3,
      "dry_roll10": 6.7,
      "springFrost": 0,
      "fallFrost": 0
    },
    "1982": {
      "heat": 22,
      "muggy": 26,
      "rain": 20,
      "snow": 0,
      "mosquito": 345,
      "dry": 6,
      "heat_roll5": 11.6,
      "muggy_roll5": 12.2,
      "rain_roll5": 19.0,
      "snow_roll5": 0.0,
      "mosquito_roll5": 347.6,
      "dry_roll5": 6.6,
      "heat_roll10": 8.1,
      "muggy_roll10": 8.8,
      "rain_roll10": 16.1,
      "snow_roll10": 0.0,
      "mosquito_roll10": 347.2,
      "dry_roll10": 6.7,
      "springFrost": 0,
      "fallFrost": 0
    },
    "1983": {
      "heat": 11,
      "muggy": 11,
      "rain": 10,
      "snow": 0,
      "mosquito": 332,
      "dry": 8,
      "heat_roll5": 12.6,
      "muggy_roll5": 13.2,
      "rain_roll5": 14.0,
      "snow_roll5": 0.0,
      "mosquito_roll5": 344.6,
      "dry_roll5": 6.8,
      "heat_roll10": 7.7,
      "muggy_roll10": 8.2,
      "rain_roll10": 15.6,
      "snow_roll10": 0.0,
      "mosquito_roll10": 344.4,
      "dry_roll10": 7.2,
      "springFrost": 0,
      "fallFrost": 0
    },
    "1984": {
      "heat": 4,
      "muggy": 3,
      "rain": 15,
      "snow": 0,
      "mosquito": 351,
      "dry": 11,
      "heat_roll5": 10.6,
      "muggy_roll5": 11.2,
      "rain_roll5": 14.0,
      "snow_roll5": 0.0,
      "mosquito_roll5": 347.4,
      "dry_roll5": 7.0,
      "heat_roll10": 8.0,
      "muggy_roll10": 8.3,
      "rain_roll10": 15.0,
      "snow_roll10": 0.0,
      "mosquito_roll10": 345.3,
      "dry_roll10": 7.3,
      "springFrost": 0,
      "fallFrost": 0
    },
    "1985": {
      "heat": 3,
      "muggy": 4,
      "rain": 10,
      "snow": 0,
      "mosquito": 354,
      "dry": 5,
      "heat_roll5": 9.0,
      "muggy_roll5": 9.8,
      "rain_roll5": 14.4,
      "snow_roll5": 0.0,
      "mosquito_roll5": 347.4,
      "dry_roll5": 7.0,
      "heat_roll10": 8.3,
      "muggy_roll10": 8.7,
      "rain_roll10": 15.1,
      "snow_roll10": 0.0,
      "mosquito_roll10": 344.9,
      "dry_roll10": 7.4,
      "springFrost": 0,
      "fallFrost": 0
    },
    "1986": {
      "heat": 6,
      "muggy": 5,
      "rain": 21,
      "snow": 0,
      "mosquito": 350,
      "dry": 8,
      "heat_roll5": 9.2,
      "muggy_roll5": 9.8,
      "rain_roll5": 15.2,
      "snow_roll5": 0.0,
      "mosquito_roll5": 346.4,
      "dry_roll5": 7.6,
      "heat_roll10": 8.9,
      "muggy_roll10": 9.1,
      "rain_roll10": 16.4,
      "snow_roll10": 0.0,
      "mosquito_roll10": 345.4,
      "dry_roll10": 7.4,
      "springFrost": 0,
      "fallFrost": 0
    },
    "1987": {
      "heat": 15,
      "muggy": 14,
      "rain": 9,
      "snow": 0,
      "mosquito": 288,
      "dry": 16,
      "heat_roll5": 7.8,
      "muggy_roll5": 7.4,
      "rain_roll5": 13.0,
      "snow_roll5": 0.0,
      "mosquito_roll5": 335.0,
      "dry_roll5": 9.6,
      "heat_roll10": 9.7,
      "muggy_roll10": 9.8,
      "rain_roll10": 16.0,
      "snow_roll10": 0.0,
      "mosquito_roll10": 341.3,
      "dry_roll10": 8.1,
      "springFrost": 0,
      "fallFrost": 0
    },
    "1988": {
      "heat": 16,
      "muggy": 16,
      "rain": 28,
      "snow": 0,
      "mosquito": 365,
      "dry": 3,
      "heat_roll5": 8.8,
      "muggy_roll5": 8.4,
      "rain_roll5": 16.6,
      "snow_roll5": 0.0,
      "mosquito_roll5": 341.6,
      "dry_roll5": 8.6,
      "heat_roll10": 10.7,
      "muggy_roll10": 10.8,
      "rain_roll10": 15.3,
      "snow_roll10": 0.0,
      "mosquito_roll10": 343.1,
      "dry_roll10": 7.7,
      "springFrost": 0,
      "fallFrost": 0
    },
    "1989": {
      "heat": 2,
      "muggy": 2,
      "rain": 19,
      "snow": 0,
      "mosquito": 335,
      "dry": 9,
      "heat_roll5": 8.4,
      "muggy_roll5": 8.2,
      "rain_roll5": 17.4,
      "snow_roll5": 0.0,
      "mosquito_roll5": 338.4,
      "dry_roll5": 8.2,
      "heat_roll10": 9.5,
      "muggy_roll10": 9.7,
      "rain_roll10": 15.7,
      "snow_roll10": 0.0,
      "mosquito_roll10": 342.9,
      "dry_roll10": 7.6,
      "springFrost": 0,
      "fallFrost": 0
    },
    "1990": {
      "heat": 9,
      "muggy": 10,
      "rain": 21,
      "snow": 0,
      "mosquito": 336,
      "dry": 10,
      "heat_roll5": 9.6,
      "muggy_roll5": 9.4,
      "rain_roll5": 19.6,
      "snow_roll5": 0.0,
      "mosquito_roll5": 334.8,
      "dry_roll5": 9.2,
      "heat_roll10": 9.3,
      "muggy_roll10": 9.6,
      "rain_roll10": 17.0,
      "snow_roll10": 0.0,
      "mosquito_roll10": 341.1,
      "dry_roll10": 8.1,
      "springFrost": 0,
      "fallFrost": 0
    },
    "1991": {
      "heat": 25,
      "muggy": 25,
      "rain": 13,
      "snow": 0,
      "mosquito": 349,
      "dry": 5,
      "heat_roll5": 13.4,
      "muggy_roll5": 13.4,
      "rain_roll5": 18.0,
      "snow_roll5": 0.0,
      "mosquito_roll5": 334.6,
      "dry_roll5": 8.6,
      "heat_roll10": 11.3,
      "muggy_roll10": 11.6,
      "rain_roll10": 16.6,
      "snow_roll10": 0.0,
      "mosquito_roll10": 340.5,
      "dry_roll10": 8.1,
      "springFrost": 0,
      "fallFrost": 0
    },
    "1992": {
      "heat": 11,
      "muggy": 13,
      "rain": 13,
      "snow": 0,
      "mosquito": 340,
      "dry": 9,
      "heat_roll5": 12.6,
      "muggy_roll5": 13.2,
      "rain_roll5": 18.8,
      "snow_roll5": 0.0,
      "mosquito_roll5": 345.0,
      "dry_roll5": 7.2,
      "heat_roll10": 10.2,
      "muggy_roll10": 10.3,
      "rain_roll10": 15.9,
      "snow_roll10": 0.0,
      "mosquito_roll10": 340.0,
      "dry_roll10": 8.4,
      "springFrost": 0,
      "fallFrost": 0
    },
    "1993": {
      "heat": 11,
      "muggy": 12,
      "rain": 14,
      "snow": 0,
      "mosquito": 341,
      "dry": 9,
      "heat_roll5": 11.6,
      "muggy_roll5": 12.4,
      "rain_roll5": 16.0,
      "snow_roll5": 0.0,
      "mosquito_roll5": 340.2,
      "dry_roll5": 8.4,
      "heat_roll10": 10.2,
      "muggy_roll10": 10.4,
      "rain_roll10": 16.3,
      "snow_roll10": 0.0,
      "mosquito_roll10": 340.9,
      "dry_roll10": 8.5,
      "springFrost": 0,
      "fallFrost": 0
    },
    "1994": {
      "heat": 10,
      "muggy": 10,
      "rain": 17,
      "snow": 0,
      "mosquito": 351,
      "dry": 7,
      "heat_roll5": 13.2,
      "muggy_roll5": 14.0,
      "rain_roll5": 15.6,
      "snow_roll5": 0.0,
      "mosquito_roll5": 343.4,
      "dry_roll5": 8.0,
      "heat_roll10": 10.8,
      "muggy_roll10": 11.1,
      "rain_roll10": 16.5,
      "snow_roll10": 0.0,
      "mosquito_roll10": 340.9,
      "dry_roll10": 8.1,
      "springFrost": 0,
      "fallFrost": 0
    },
    "1995": {
      "heat": 11,
      "muggy": 11,
      "rain": 12,
      "snow": 0,
      "mosquito": 362,
      "dry": 5,
      "heat_roll5": 13.6,
      "muggy_roll5": 14.2,
      "rain_roll5": 13.8,
      "snow_roll5": 0.0,
      "mosquito_roll5": 348.6,
      "dry_roll5": 7.0,
      "heat_roll10": 11.6,
      "muggy_roll10": 11.8,
      "rain_roll10": 16.7,
      "snow_roll10": 0.0,
      "mosquito_roll10": 341.7,
      "dry_roll10": 8.1,
      "springFrost": 0,
      "fallFrost": 0
    },
    "1996": {
      "heat": 6,
      "muggy": 6,
      "rain": 15,
      "snow": 0,
      "mosquito": 360,
      "dry": 5,
      "heat_roll5": 9.8,
      "muggy_roll5": 10.4,
      "rain_roll5": 14.2,
      "snow_roll5": 0.0,
      "mosquito_roll5": 350.8,
      "dry_roll5": 7.0,
      "heat_roll10": 11.6,
      "muggy_roll10": 11.9,
      "rain_roll10": 16.1,
      "snow_roll10": 0.0,
      "mosquito_roll10": 342.7,
      "dry_roll10": 7.8,
      "springFrost": 0,
      "fallFrost": 0
    },
    "1997": {
      "heat": 8,
      "muggy": 11,
      "rain": 26,
      "snow": 0,
      "mosquito": 337,
      "dry": 7,
      "heat_roll5": 9.2,
      "muggy_roll5": 10.0,
      "rain_roll5": 16.8,
      "snow_roll5": 0.0,
      "mosquito_roll5": 350.2,
      "dry_roll5": 6.6,
      "heat_roll10": 10.9,
      "muggy_roll10": 11.6,
      "rain_roll10": 17.8,
      "snow_roll10": 0.0,
      "mosquito_roll10": 347.6,
      "dry_roll10": 6.9,
      "springFrost": 0,
      "fallFrost": 0
    },
    "1998": {
      "heat": 10,
      "muggy": 12,
      "rain": 18,
      "snow": 0,
      "mosquito": 331,
      "dry": 8,
      "heat_roll5": 9.0,
      "muggy_roll5": 10.0,
      "rain_roll5": 17.6,
      "snow_roll5": 0.0,
      "mosquito_roll5": 348.2,
      "dry_roll5": 6.4,
      "heat_roll10": 10.3,
      "muggy_roll10": 11.2,
      "rain_roll10": 16.8,
      "snow_roll10": 0.0,
      "mosquito_roll10": 344.2,
      "dry_roll10": 7.4,
      "springFrost": 0,
      "fallFrost": 0
    },
    "1999": {
      "heat": 11,
      "muggy": 14,
      "rain": 14,
      "snow": 0,
      "mosquito": 354,
      "dry": 5,
      "heat_roll5": 9.2,
      "muggy_roll5": 10.8,
      "rain_roll5": 17.0,
      "snow_roll5": 0.0,
      "mosquito_roll5": 348.8,
      "dry_roll5": 6.0,
      "heat_roll10": 11.2,
      "muggy_roll10": 12.4,
      "rain_roll10": 16.3,
      "snow_roll10": 0.0,
      "mosquito_roll10": 346.1,
      "dry_roll10": 7.0,
      "springFrost": 0,
      "fallFrost": 0
    },
    "2000": {
      "heat": 4,
      "muggy": 5,
      "rain": 14,
      "snow": 0,
      "mosquito": 362,
      "dry": 4,
      "heat_roll5": 7.8,
      "muggy_roll5": 9.6,
      "rain_roll5": 17.4,
      "snow_roll5": 0.0,
      "mosquito_roll5": 348.8,
      "dry_roll5": 5.8,
      "heat_roll10": 10.7,
      "muggy_roll10": 11.9,
      "rain_roll10": 15.6,
      "snow_roll10": 0.0,
      "mosquito_roll10": 348.7,
      "dry_roll10": 6.4,
      "springFrost": 0,
      "fallFrost": 0
    },
    "2001": {
      "heat": 12,
      "muggy": 16,
      "rain": 22,
      "snow": 0,
      "mosquito": 346,
      "dry": 6,
      "heat_roll5": 9.0,
      "muggy_roll5": 11.6,
      "rain_roll5": 18.8,
      "snow_roll5": 0.0,
      "mosquito_roll5": 346.0,
      "dry_roll5": 6.0,
      "heat_roll10": 9.4,
      "muggy_roll10": 11.0,
      "rain_roll10": 16.5,
      "snow_roll10": 0.0,
      "mosquito_roll10": 348.4,
      "dry_roll10": 6.5,
      "springFrost": 0,
      "fallFrost": 0
    },
    "2002": {
      "heat": 45,
      "muggy": 42,
      "rain": 20,
      "snow": 0,
      "mosquito": 350,
      "dry": 7,
      "heat_roll5": 16.4,
      "muggy_roll5": 17.8,
      "rain_roll5": 17.6,
      "snow_roll5": 0.0,
      "mosquito_roll5": 348.6,
      "dry_roll5": 6.0,
      "heat_roll10": 12.8,
      "muggy_roll10": 13.9,
      "rain_roll10": 17.2,
      "snow_roll10": 0.0,
      "mosquito_roll10": 349.4,
      "dry_roll10": 6.3,
      "springFrost": 0,
      "fallFrost": 0
    },
    "2003": {
      "heat": 40,
      "muggy": 33,
      "rain": 24,
      "snow": 0,
      "mosquito": 344,
      "dry": 8,
      "heat_roll5": 22.4,
      "muggy_roll5": 22.0,
      "rain_roll5": 18.8,
      "snow_roll5": 0.0,
      "mosquito_roll5": 351.2,
      "dry_roll5": 6.0,
      "heat_roll10": 15.7,
      "muggy_roll10": 16.0,
      "rain_roll10": 18.2,
      "snow_roll10": 0.0,
      "mosquito_roll10": 349.7,
      "dry_roll10": 6.2,
      "springFrost": 0,
      "fallFrost": 0
    },
    "2004": {
      "heat": 43,
      "muggy": 40,
      "rain": 29,
      "snow": 0,
      "mosquito": 345,
      "dry": 8,
      "heat_roll5": 28.8,
      "muggy_roll5": 27.2,
      "rain_roll5": 21.8,
      "snow_roll5": 0.0,
      "mosquito_roll5": 349.4,
      "dry_roll5": 6.6,
      "heat_roll10": 19.0,
      "muggy_roll10": 19.0,
      "rain_roll10": 19.4,
      "snow_roll10": 0.0,
      "mosquito_roll10": 349.1,
      "dry_roll10": 6.3,
      "springFrost": 0,
      "fallFrost": 0
    },
    "2005": {
      "heat": 53,
      "muggy": 47,
      "rain": 14,
      "snow": 0,
      "mosquito": 347,
      "dry": 6,
      "heat_roll5": 38.6,
      "muggy_roll5": 35.6,
      "rain_roll5": 21.8,
      "snow_roll5": 0.0,
      "mosquito_roll5": 346.4,
      "dry_roll5": 7.0,
      "heat_roll10": 23.2,
      "muggy_roll10": 22.6,
      "rain_roll10": 19.6,
      "snow_roll10": 0.0,
      "mosquito_roll10": 347.6,
      "dry_roll10": 6.4,
      "springFrost": 0,
      "fallFrost": 0
    },
    "2006": {
      "heat": 20,
      "muggy": 21,
      "rain": 32,
      "snow": 0,
      "mosquito": 356,
      "dry": 8,
      "heat_roll5": 40.2,
      "muggy_roll5": 36.6,
      "rain_roll5": 23.8,
      "snow_roll5": 0.0,
      "mosquito_roll5": 348.4,
      "dry_roll5": 7.4,
      "heat_roll10": 24.6,
      "muggy_roll10": 24.1,
      "rain_roll10": 21.3,
      "snow_roll10": 0.0,
      "mosquito_roll10": 347.2,
      "dry_roll10": 6.7,
      "springFrost": 0,
      "fallFrost": 0
    },
    "2007": {
      "heat": 36,
      "muggy": 38,
      "rain": 19,
      "snow": 0,
      "mosquito": 360,
      "dry": 4,
      "heat_roll5": 38.4,
      "muggy_roll5": 35.8,
      "rain_roll5": 23.6,
      "snow_roll5": 0.0,
      "mosquito_roll5": 350.4,
      "dry_roll5": 6.8,
      "heat_roll10": 27.4,
      "muggy_roll10": 26.8,
      "rain_roll10": 20.6,
      "snow_roll10": 0.0,
      "mosquito_roll10": 349.5,
      "dry_roll10": 6.4,
      "springFrost": 0,
      "fallFrost": 0
    },
    "2008": {
      "heat": 6,
      "muggy": 5,
      "rain": 17,
      "snow": 0,
      "mosquito": 362,
      "dry": 4,
      "heat_roll5": 31.6,
      "muggy_roll5": 30.2,
      "rain_roll5": 22.2,
      "snow_roll5": 0.0,
      "mosquito_roll5": 354.0,
      "dry_roll5": 6.0,
      "heat_roll10": 27.0,
      "muggy_roll10": 26.1,
      "rain_roll10": 20.5,
      "snow_roll10": 0.0,
      "mosquito_roll10": 352.6,
      "dry_roll10": 6.0,
      "springFrost": 0,
      "fallFrost": 0
    },
    "2009": {
      "heat": 18,
      "muggy": 18,
      "rain": 17,
      "snow": 0,
      "mosquito": 338,
      "dry": 12,
      "heat_roll5": 26.6,
      "muggy_roll5": 25.8,
      "rain_roll5": 19.8,
      "snow_roll5": 0.0,
      "mosquito_roll5": 352.6,
      "dry_roll5": 6.8,
      "heat_roll10": 27.7,
      "muggy_roll10": 26.5,
      "rain_roll10": 20.8,
      "snow_roll10": 0.0,
      "mosquito_roll10": 351.0,
      "dry_roll10": 6.7,
      "springFrost": 0,
      "fallFrost": 0
    },
    "2010": {
      "heat": 52,
      "muggy": 50,
      "rain": 21,
      "snow": 0,
      "mosquito": 355,
      "dry": 6,
      "heat_roll5": 26.4,
      "muggy_roll5": 26.4,
      "rain_roll5": 21.2,
      "snow_roll5": 0.0,
      "mosquito_roll5": 354.2,
      "dry_roll5": 6.8,
      "heat_roll10": 32.5,
      "muggy_roll10": 31.0,
      "rain_roll10": 21.5,
      "snow_roll10": 0.0,
      "mosquito_roll10": 350.3,
      "dry_roll10": 6.9,
      "springFrost": 0,
      "fallFrost": 0
    },
    "2011": {
      "heat": 5,
      "muggy": 6,
      "rain": 24,
      "snow": 0,
      "mosquito": 332,
      "dry": 7,
      "heat_roll5": 23.4,
      "muggy_roll5": 23.4,
      "rain_roll5": 19.6,
      "snow_roll5": 0.0,
      "mosquito_roll5": 349.4,
      "dry_roll5": 6.6,
      "heat_roll10": 31.8,
      "muggy_roll10": 30.0,
      "rain_roll10": 21.7,
      "snow_roll10": 0.0,
      "mosquito_roll10": 348.9,
      "dry_roll10": 7.0,
      "springFrost": 0,
      "fallFrost": 0
    },
    "2012": {
      "heat": 11,
      "muggy": 11,
      "rain": 15,
      "snow": 0,
      "mosquito": 353,
      "dry": 6,
      "heat_roll5": 18.4,
      "muggy_roll5": 18.0,
      "rain_roll5": 18.8,
      "snow_roll5": 0.0,
      "mosquito_roll5": 348.0,
      "dry_roll5": 7.0,
      "heat_roll10": 28.4,
      "muggy_roll10": 26.9,
      "rain_roll10": 21.2,
      "snow_roll10": 0.0,
      "mosquito_roll10": 349.2,
      "dry_roll10": 6.9,
      "springFrost": 0,
      "fallFrost": 0
    },
    "2013": {
      "heat": 30,
      "muggy": 32,
      "rain": 32,
      "snow": 0,
      "mosquito": 358,
      "dry": 4,
      "heat_roll5": 23.2,
      "muggy_roll5": 23.4,
      "rain_roll5": 21.8,
      "snow_roll5": 0.0,
      "mosquito_roll5": 347.2,
      "dry_roll5": 7.0,
      "heat_roll10": 27.4,
      "muggy_roll10": 26.8,
      "rain_roll10": 22.0,
      "snow_roll10": 0.0,
      "mosquito_roll10": 350.6,
      "dry_roll10": 6.5,
      "springFrost": 0,
      "fallFrost": 0
    },
    "2014": {
      "heat": 19,
      "muggy": 19,
      "rain": 22,
      "snow": 0,
      "mosquito": 348,
      "dry": 9,
      "heat_roll5": 23.4,
      "muggy_roll5": 23.6,
      "rain_roll5": 22.8,
      "snow_roll5": 0.0,
      "mosquito_roll5": 349.2,
      "dry_roll5": 6.4,
      "heat_roll10": 25.0,
      "muggy_roll10": 24.7,
      "rain_roll10": 21.3,
      "snow_roll10": 0.0,
      "mosquito_roll10": 350.9,
      "dry_roll10": 6.6,
      "springFrost": 0,
      "fallFrost": 0
    },
    "2015": {
      "heat": 38,
      "muggy": 37,
      "rain": 18,
      "snow": 0,
      "mosquito": 335,
      "dry": 7,
      "heat_roll5": 20.6,
      "muggy_roll5": 21.0,
      "rain_roll5": 22.2,
      "snow_roll5": 0.0,
      "mosquito_roll5": 345.2,
      "dry_roll5": 6.6,
      "heat_roll10": 23.5,
      "muggy_roll10": 23.7,
      "rain_roll10": 21.7,
      "snow_roll10": 0.0,
      "mosquito_roll10": 349.7,
      "dry_roll10": 6.7,
      "springFrost": 0,
      "fallFrost": 0
    },
    "2016": {
      "heat": 97,
      "muggy": 94,
      "rain": 21,
      "snow": 0,
      "mosquito": 346,
      "dry": 11,
      "heat_roll5": 39.0,
      "muggy_roll5": 38.6,
      "rain_roll5": 21.6,
      "snow_roll5": 0.0,
      "mosquito_roll5": 348.0,
      "dry_roll5": 7.4,
      "heat_roll10": 31.2,
      "muggy_roll10": 31.0,
      "rain_roll10": 20.6,
      "snow_roll10": 0.0,
      "mosquito_roll10": 348.7,
      "dry_roll10": 7.0,
      "springFrost": 0,
      "fallFrost": 0
    },
    "2017": {
      "heat": 51,
      "muggy": 49,
      "rain": 41,
      "snow": 0,
      "mosquito": 352,
      "dry": 8,
      "heat_roll5": 47.0,
      "muggy_roll5": 46.2,
      "rain_roll5": 26.8,
      "snow_roll5": 0.0,
      "mosquito_roll5": 347.8,
      "dry_roll5": 7.8,
      "heat_roll10": 32.7,
      "muggy_roll10": 32.1,
      "rain_roll10": 22.8,
      "snow_roll10": 0.0,
      "mosquito_roll10": 347.9,
      "dry_roll10": 7.4,
      "springFrost": 0,
      "fallFrost": 0
    },
    "2018": {
      "heat": 42,
      "muggy": 40,
      "rain": 25,
      "snow": 0,
      "mosquito": 346,
      "dry": 8,
      "heat_roll5": 49.4,
      "muggy_roll5": 47.8,
      "rain_roll5": 25.4,
      "snow_roll5": 0.0,
      "mosquito_roll5": 345.4,
      "dry_roll5": 8.6,
      "heat_roll10": 36.3,
      "muggy_roll10": 35.6,
      "rain_roll10": 23.6,
      "snow_roll10": 0.0,
      "mosquito_roll10": 346.3,
      "dry_roll10": 7.8,
      "springFrost": 0,
      "fallFrost": 0
    },
    "2019": {
      "heat": 66,
      "muggy": 63,
      "rain": 29,
      "snow": 0,
      "mosquito": 363,
      "dry": 3,
      "heat_roll5": 58.8,
      "muggy_roll5": 56.6,
      "rain_roll5": 26.8,
      "snow_roll5": 0.0,
      "mosquito_roll5": 348.4,
      "dry_roll5": 7.4,
      "heat_roll10": 41.1,
      "muggy_roll10": 40.1,
      "rain_roll10": 24.8,
      "snow_roll10": 0.0,
      "mosquito_roll10": 348.8,
      "dry_roll10": 6.9,
      "springFrost": 0,
      "fallFrost": 0
    },
    "2020": {
      "heat": 64,
      "muggy": 66,
      "rain": 30,
      "snow": 0,
      "mosquito": 348,
      "dry": 6,
      "heat_roll5": 64.0,
      "muggy_roll5": 62.4,
      "rain_roll5": 29.2,
      "snow_roll5": 0.0,
      "mosquito_roll5": 351.0,
      "dry_roll5": 7.2,
      "heat_roll10": 42.3,
      "muggy_roll10": 41.7,
      "rain_roll10": 25.7,
      "snow_roll10": 0.0,
      "mosquito_roll10": 348.1,
      "dry_roll10": 6.9,
      "springFrost": 0,
      "fallFrost": 0
    },
    "2021": {
      "heat": 26,
      "muggy": 27,
      "rain": 20,
      "snow": 0,
      "mosquito": 345,
      "dry": 11,
      "heat_roll5": 49.8,
      "muggy_roll5": 49.0,
      "rain_roll5": 29.0,
      "snow_roll5": 0.0,
      "mosquito_roll5": 350.8,
      "dry_roll5": 7.2,
      "heat_roll10": 44.4,
      "muggy_roll10": 43.8,
      "rain_roll10": 25.3,
      "snow_roll10": 0.0,
      "mosquito_roll10": 349.4,
      "dry_roll10": 7.3,
      "springFrost": 0,
      "fallFrost": 0
    },
    "2022": {
      "heat": 17,
      "muggy": 20,
      "rain": 18,
      "snow": 0,
      "mosquito": 360,
      "dry": 3,
      "heat_roll5": 43.0,
      "muggy_roll5": 43.2,
      "rain_roll5": 24.4,
      "snow_roll5": 0.0,
      "mosquito_roll5": 352.4,
      "dry_roll5": 6.2,
      "heat_roll10": 45.0,
      "muggy_roll10": 44.7,
      "rain_roll10": 25.6,
      "snow_roll10": 0.0,
      "mosquito_roll10": 350.1,
      "dry_roll10": 7.0,
      "springFrost": 0,
      "fallFrost": 0
    },
    "2023": {
      "heat": 75,
      "muggy": 72,
      "rain": 21,
      "snow": 0,
      "mosquito": 344,
      "dry": 7,
      "heat_roll5": 49.6,
      "muggy_roll5": 49.6,
      "rain_roll5": 23.6,
      "snow_roll5": 0.0,
      "mosquito_roll5": 352.0,
      "dry_roll5": 6.0,
      "heat_roll10": 49.5,
      "muggy_roll10": 48.7,
      "rain_roll10": 24.5,
      "snow_roll10": 0.0,
      "mosquito_roll10": 348.7,
      "dry_roll10": 7.3,
      "springFrost": 0,
      "fallFrost": 0
    },
    "2024": {
      "heat": 144,
      "muggy": 135,
      "rain": 24,
      "snow": 0,
      "mosquito": 345,
      "dry": 10,
      "heat_roll5": 65.2,
      "muggy_roll5": 64.0,
      "rain_roll5": 22.6,
      "snow_roll5": 0.0,
      "mosquito_roll5": 348.4,
      "dry_roll5": 7.4,
      "heat_roll10": 62.0,
      "muggy_roll10": 60.3,
      "rain_roll10": 24.7,
      "snow_roll10": 0.0,
      "mosquito_roll10": 348.4,
      "dry_roll10": 7.4,
      "springFrost": 0,
      "fallFrost": 0
    },
    "2025": {
      "heat": 62,
      "muggy": 50,
      "rain": 26,
      "snow": 0,
      "mosquito": 308,
      "dry": 5,
      "heat_roll5": 64.8,
      "muggy_roll5": 60.8,
      "rain_roll5": 21.8,
      "snow_roll5": 0.0,
      "mosquito_roll5": 340.4,
      "dry_roll5": 7.2,
      "heat_roll10": 64.4,
      "muggy_roll10": 61.6,
      "rain_roll10": 25.5,
      "snow_roll10": 0.0,
      "mosquito_roll10": 345.7,
      "dry_roll10": 7.2,
      "springFrost": 0,
      "fallFrost": 0
    }
  },
  "scenarios": {
    "ssp126": {
      "2026": {
        "heat": 79,
        "muggy": 107,
        "rain": 30,
        "snow": 0,
        "mosquito": 355,
        "dry": 1,
        "heat_roll5": 75.4,
        "muggy_roll5": 76.8,
        "rain_roll5": 23.8,
        "snow_roll5": 0.0,
        "mosquito_roll5": 342.4,
        "dry_roll5": 5.2,
        "heat_roll10": 62.6,
        "muggy_roll10": 62.9,
        "rain_roll10": 26.4,
        "snow_roll10": 0.0,
        "mosquito_roll10": 346.6,
        "dry_roll10": 6.2,
        "heat_trend": 67.4,
        "muggy_trend": 62.8,
        "rain_trend": 22.4,
        "snow_trend": 0.0,
        "mosquito_trend": 342.2,
        "dry_trend": 7.2,
        "springFrost": 0,
        "fallFrost": 0
      },
      "2027": {
        "heat": 68,
        "muggy": 28,
        "rain": 24,
        "snow": 0,
        "mosquito": 378,
        "dry": 1,
        "heat_roll5": 85.6,
        "muggy_roll5": 78.4,
        "rain_roll5": 25.0,
        "snow_roll5": 0.0,
        "mosquito_roll5": 346.0,
        "dry_roll5": 4.8,
        "heat_roll10": 64.3,
        "muggy_roll10": 60.8,
        "rain_roll10": 24.7,
        "snow_roll10": 0.0,
        "mosquito_roll10": 349.2,
        "dry_roll10": 5.5,
        "heat_trend": 70.0,
        "muggy_trend": 64.8,
        "rain_trend": 22.9,
        "snow_trend": 0.0,
        "mosquito_trend": 343.8,
        "dry_trend": 7.2,
        "springFrost": 0,
        "fallFrost": 0
      },
      "2028": {
        "heat": 53,
        "muggy": 36,
        "rain": 36,
        "snow": 0,
        "mosquito": 358,
        "dry": 4,
        "heat_roll5": 81.2,
        "muggy_roll5": 71.2,
        "rain_roll5": 28.0,
        "snow_roll5": 0.0,
        "mosquito_roll5": 348.8,
        "dry_roll5": 4.2,
        "heat_roll10": 65.4,
        "muggy_roll10": 60.4,
        "rain_roll10": 25.8,
        "snow_roll10": 0.0,
        "mosquito_roll10": 350.4,
        "dry_roll10": 5.1,
        "heat_trend": 72.4,
        "muggy_trend": 66.6,
        "rain_trend": 23.4,
        "snow_trend": 0.0,
        "mosquito_trend": 345.4,
        "dry_trend": 7.2,
        "springFrost": 0,
        "fallFrost": 0
      },
      "2029": {
        "heat": 108,
        "muggy": 80,
        "rain": 30,
        "snow": 0,
        "mosquito": 360,
        "dry": 5,
        "heat_roll5": 74.0,
        "muggy_roll5": 60.2,
        "rain_roll5": 29.2,
        "snow_roll5": 0.0,
        "mosquito_roll5": 351.8,
        "dry_roll5": 3.2,
        "heat_roll10": 69.6,
        "muggy_roll10": 62.1,
        "rain_roll10": 25.9,
        "snow_roll10": 0.0,
        "mosquito_roll10": 350.1,
        "dry_roll10": 5.3,
        "heat_trend": 74.9,
        "muggy_trend": 68.4,
        "rain_trend": 23.8,
        "snow_trend": 0.0,
        "mosquito_trend": 346.9,
        "dry_trend": 7.1,
        "springFrost": 0,
        "fallFrost": 0
      },
      "2030": {
        "heat": 73,
        "muggy": 106,
        "rain": 26,
        "snow": 0,
        "mosquito": 303,
        "dry": 14,
        "heat_roll5": 76.2,
        "muggy_roll5": 71.4,
        "rain_roll5": 29.2,
        "snow_roll5": 0.0,
        "mosquito_roll5": 350.8,
        "dry_roll5": 5.0,
        "heat_roll10": 70.5,
        "muggy_roll10": 66.1,
        "rain_roll10": 25.5,
        "snow_roll10": 0.0,
        "mosquito_roll10": 345.6,
        "dry_roll10": 6.1,
        "heat_trend": 77.2,
        "muggy_trend": 70.0,
        "rain_trend": 24.3,
        "snow_trend": 0.0,
        "mosquito_trend": 348.3,
        "dry_trend": 7.1,
        "springFrost": 0,
        "fallFrost": 0
      },
      "2031": {
        "heat": 68,
        "muggy": 113,
        "rain": 10,
        "snow": 0,
        "mosquito": 318,
        "dry": 10,
        "heat_roll5": 74.0,
        "muggy_roll5": 72.6,
        "rain_roll5": 25.2,
        "snow_roll5": 0.0,
        "mosquito_roll5": 343.4,
        "dry_roll5": 6.8,
        "heat_roll10": 74.7,
        "muggy_roll10": 74.7,
        "rain_roll10": 24.5,
        "snow_roll10": 0.0,
        "mosquito_roll10": 342.9,
        "dry_roll10": 6.0,
        "heat_trend": 79.5,
        "muggy_trend": 71.5,
        "rain_trend": 24.7,
        "snow_trend": 0.0,
        "mosquito_trend": 349.7,
        "dry_trend": 7.0,
        "springFrost": 0,
        "fallFrost": 0
      },
      "2032": {
        "heat": 116,
        "muggy": 115,
        "rain": 22,
        "snow": 0,
        "mosquito": 363,
        "dry": 5,
        "heat_roll5": 83.6,
        "muggy_roll5": 90.0,
        "rain_roll5": 24.8,
        "snow_roll5": 0.0,
        "mosquito_roll5": 340.4,
        "dry_roll5": 7.6,
        "heat_roll10": 84.6,
        "muggy_roll10": 84.2,
        "rain_roll10": 24.9,
        "snow_roll10": 0.0,
        "mosquito_roll10": 343.2,
        "dry_roll10": 6.2,
        "heat_trend": 81.7,
        "muggy_trend": 72.9,
        "rain_trend": 25.1,
        "snow_trend": 0.0,
        "mosquito_trend": 350.9,
        "dry_trend": 6.9,
        "springFrost": 0,
        "fallFrost": 0
      },
      "2033": {
        "heat": 46,
        "muggy": 25,
        "rain": 42,
        "snow": 0,
        "mosquito": 377,
        "dry": 2,
        "heat_roll5": 82.2,
        "muggy_roll5": 87.8,
        "rain_roll5": 26.0,
        "snow_roll5": 0.0,
        "mosquito_roll5": 344.2,
        "dry_roll5": 7.2,
        "heat_roll10": 81.7,
        "muggy_roll10": 79.5,
        "rain_roll10": 27.0,
        "snow_roll10": 0.0,
        "mosquito_roll10": 346.5,
        "dry_roll10": 5.7,
        "heat_trend": 83.8,
        "muggy_trend": 74.2,
        "rain_trend": 25.4,
        "snow_trend": 0.0,
        "mosquito_trend": 352.0,
        "dry_trend": 6.8,
        "springFrost": 0,
        "fallFrost": 0
      },
      "2034": {
        "heat": 63,
        "muggy": 36,
        "rain": 20,
        "snow": 0,
        "mosquito": 367,
        "dry": 3,
        "heat_roll5": 73.2,
        "muggy_roll5": 79.0,
        "rain_roll5": 24.0,
        "snow_roll5": 0.0,
        "mosquito_roll5": 345.6,
        "dry_roll5": 6.8,
        "heat_roll10": 73.6,
        "muggy_roll10": 69.6,
        "rain_roll10": 26.6,
        "snow_roll10": 0.0,
        "mosquito_roll10": 348.7,
        "dry_roll10": 5.0,
        "heat_trend": 85.9,
        "muggy_trend": 75.5,
        "rain_trend": 25.7,
        "snow_trend": 0.0,
        "mosquito_trend": 353.1,
        "dry_trend": 6.7,
        "springFrost": 0,
        "fallFrost": 0
      },
      "2035": {
        "heat": 95,
        "muggy": 102,
        "rain": 24,
        "snow": 0,
        "mosquito": 326,
        "dry": 10,
        "heat_roll5": 77.6,
        "muggy_roll5": 78.2,
        "rain_roll5": 23.6,
        "snow_roll5": 0.0,
        "mosquito_roll5": 350.2,
        "dry_roll5": 6.0,
        "heat_roll10": 76.9,
        "muggy_roll10": 74.8,
        "rain_roll10": 26.4,
        "snow_roll10": 0.0,
        "mosquito_roll10": 350.5,
        "dry_roll10": 5.5,
        "heat_trend": 87.9,
        "muggy_trend": 76.6,
        "rain_trend": 26.0,
        "snow_trend": 0.0,
        "mosquito_trend": 354.1,
        "dry_trend": 6.6,
        "springFrost": 0,
        "fallFrost": 0
      },
      "2036": {
        "heat": 105,
        "muggy": 138,
        "rain": 22,
        "snow": 0,
        "mosquito": 330,
        "dry": 20,
        "heat_roll5": 85.0,
        "muggy_roll5": 83.2,
        "rain_roll5": 26.0,
        "snow_roll5": 0.0,
        "mosquito_roll5": 352.6,
        "dry_roll5": 8.0,
        "heat_roll10": 79.5,
        "muggy_roll10": 77.9,
        "rain_roll10": 25.6,
        "snow_roll10": 0.0,
        "mosquito_roll10": 348.0,
        "dry_roll10": 7.4,
        "heat_trend": 89.8,
        "muggy_trend": 77.6,
        "rain_trend": 26.3,
        "snow_trend": 0.0,
        "mosquito_trend": 355.0,
        "dry_trend": 6.5,
        "springFrost": 0,
        "fallFrost": 0
      },
      "2037": {
        "heat": 82,
        "muggy": 50,
        "rain": 22,
        "snow": 0,
        "mosquito": 372,
        "dry": 7,
        "heat_roll5": 78.2,
        "muggy_roll5": 70.2,
        "rain_roll5": 26.0,
        "snow_roll5": 0.0,
        "mosquito_roll5": 354.4,
        "dry_roll5": 8.4,
        "heat_roll10": 80.9,
        "muggy_roll10": 80.1,
        "rain_roll10": 25.4,
        "snow_roll10": 0.0,
        "mosquito_roll10": 347.4,
        "dry_roll10": 8.0,
        "heat_trend": 91.7,
        "muggy_trend": 78.4,
        "rain_trend": 26.5,
        "snow_trend": 0.0,
        "mosquito_trend": 355.8,
        "dry_trend": 6.3,
        "springFrost": 0,
        "fallFrost": 0
      },
      "2038": {
        "heat": 74,
        "muggy": 53,
        "rain": 8,
        "snow": 0,
        "mosquito": 358,
        "dry": 7,
        "heat_roll5": 83.8,
        "muggy_roll5": 75.8,
        "rain_roll5": 19.2,
        "snow_roll5": 0.0,
        "mosquito_roll5": 350.6,
        "dry_roll5": 9.4,
        "heat_roll10": 83.0,
        "muggy_roll10": 81.8,
        "rain_roll10": 22.6,
        "snow_roll10": 0.0,
        "mosquito_roll10": 347.4,
        "dry_roll10": 8.3,
        "heat_trend": 93.5,
        "muggy_trend": 79.2,
        "rain_trend": 26.7,
        "snow_trend": 0.0,
        "mosquito_trend": 356.5,
        "dry_trend": 6.1,
        "springFrost": 0,
        "fallFrost": 0
      },
      "2039": {
        "heat": 114,
        "muggy": 83,
        "rain": 28,
        "snow": 0,
        "mosquito": 364,
        "dry": 3,
        "heat_roll5": 94.0,
        "muggy_roll5": 85.2,
        "rain_roll5": 20.8,
        "snow_roll5": 0.0,
        "mosquito_roll5": 350.0,
        "dry_roll5": 9.4,
        "heat_roll10": 83.6,
        "muggy_roll10": 82.1,
        "rain_roll10": 22.4,
        "snow_roll10": 0.0,
        "mosquito_roll10": 347.8,
        "dry_roll10": 8.1,
        "heat_trend": 95.2,
        "muggy_trend": 79.9,
        "rain_trend": 26.9,
        "snow_trend": 0.0,
        "mosquito_trend": 357.1,
        "dry_trend": 6.0,
        "springFrost": 0,
        "fallFrost": 0
      },
      "2040": {
        "heat": 105,
        "muggy": 57,
        "rain": 38,
        "snow": 0,
        "mosquito": 369,
        "dry": 5,
        "heat_roll5": 96.0,
        "muggy_roll5": 76.2,
        "rain_roll5": 23.6,
        "snow_roll5": 0.0,
        "mosquito_roll5": 358.6,
        "dry_roll5": 8.4,
        "heat_roll10": 86.8,
        "muggy_roll10": 77.2,
        "rain_roll10": 23.6,
        "snow_roll10": 0.0,
        "mosquito_roll10": 354.4,
        "dry_roll10": 7.2,
        "heat_trend": 96.8,
        "muggy_trend": 80.5,
        "rain_trend": 27.0,
        "snow_trend": 0.0,
        "mosquito_trend": 357.7,
        "dry_trend": 5.8,
        "springFrost": 0,
        "fallFrost": 0
      },
      "2041": {
        "heat": 132,
        "muggy": 82,
        "rain": 30,
        "snow": 0,
        "mosquito": 348,
        "dry": 1,
        "heat_roll5": 101.4,
        "muggy_roll5": 65.0,
        "rain_roll5": 25.2,
        "snow_roll5": 0.0,
        "mosquito_roll5": 362.2,
        "dry_roll5": 4.6,
        "heat_roll10": 93.2,
        "muggy_roll10": 74.1,
        "rain_roll10": 25.6,
        "snow_roll10": 0.0,
        "mosquito_roll10": 357.4,
        "dry_roll10": 6.3,
        "heat_trend": 98.4,
        "muggy_trend": 81.0,
        "rain_trend": 27.1,
        "snow_trend": 0.0,
        "mosquito_trend": 358.1,
        "dry_trend": 5.6,
        "springFrost": 0,
        "fallFrost": 0
      },
      "2042": {
        "heat": 85,
        "muggy": 100,
        "rain": 24,
        "snow": 0,
        "mosquito": 342,
        "dry": 5,
        "heat_roll5": 102.0,
        "muggy_roll5": 75.0,
        "rain_roll5": 25.6,
        "snow_roll5": 0.0,
        "mosquito_roll5": 356.2,
        "dry_roll5": 4.2,
        "heat_roll10": 90.1,
        "muggy_roll10": 72.6,
        "rain_roll10": 25.8,
        "snow_roll10": 0.0,
        "mosquito_roll10": 355.3,
        "dry_roll10": 6.3,
        "heat_trend": 99.9,
        "muggy_trend": 81.4,
        "rain_trend": 27.2,
        "snow_trend": 0.0,
        "mosquito_trend": 358.5,
        "dry_trend": 5.3,
        "springFrost": 0,
        "fallFrost": 0
      },
      "2043": {
        "heat": 116,
        "muggy": 76,
        "rain": 34,
        "snow": 0,
        "mosquito": 373,
        "dry": 4,
        "heat_roll5": 110.4,
        "muggy_roll5": 79.6,
        "rain_roll5": 30.8,
        "snow_roll5": 0.0,
        "mosquito_roll5": 359.2,
        "dry_roll5": 3.6,
        "heat_roll10": 97.1,
        "muggy_roll10": 77.7,
        "rain_roll10": 25.0,
        "snow_roll10": 0.0,
        "mosquito_roll10": 354.9,
        "dry_roll10": 6.5,
        "heat_trend": 101.4,
        "muggy_trend": 81.6,
        "rain_trend": 27.2,
        "snow_trend": 0.0,
        "mosquito_trend": 358.8,
        "dry_trend": 5.1,
        "springFrost": 0,
        "fallFrost": 0
      },
      "2044": {
        "heat": 106,
        "muggy": 79,
        "rain": 36,
        "snow": 0,
        "mosquito": 390,
        "dry": 0,
        "heat_roll5": 108.8,
        "muggy_roll5": 78.8,
        "rain_roll5": 32.4,
        "snow_roll5": 0.0,
        "mosquito_roll5": 364.4,
        "dry_roll5": 3.0,
        "heat_roll10": 101.4,
        "muggy_roll10": 82.0,
        "rain_roll10": 26.6,
        "snow_roll10": 0.0,
        "mosquito_roll10": 357.2,
        "dry_roll10": 6.2,
        "heat_trend": 102.8,
        "muggy_trend": 81.8,
        "rain_trend": 27.3,
        "snow_trend": 0.0,
        "mosquito_trend": 359.0,
        "dry_trend": 4.8,
        "springFrost": 0,
        "fallFrost": 0
      },
      "2045": {
        "heat": 90,
        "muggy": 51,
        "rain": 14,
        "snow": 0,
        "mosquito": 349,
        "dry": 6,
        "heat_roll5": 105.8,
        "muggy_roll5": 77.6,
        "rain_roll5": 27.6,
        "snow_roll5": 0.0,
        "mosquito_roll5": 360.4,
        "dry_roll5": 3.2,
        "heat_roll10": 100.9,
        "muggy_roll10": 76.9,
        "rain_roll10": 25.6,
        "snow_roll10": 0.0,
        "mosquito_roll10": 359.5,
        "dry_roll10": 5.8,
        "heat_trend": 104.1,
        "muggy_trend": 81.8,
        "rain_trend": 27.3,
        "snow_trend": 0.0,
        "mosquito_trend": 359.1,
        "dry_trend": 4.6,
        "springFrost": 0,
        "fallFrost": 0
      },
      "2046": {
        "heat": 93,
        "muggy": 59,
        "rain": 38,
        "snow": 0,
        "mosquito": 367,
        "dry": 3,
        "heat_roll5": 98.0,
        "muggy_roll5": 73.0,
        "rain_roll5": 29.2,
        "snow_roll5": 0.0,
        "mosquito_roll5": 364.2,
        "dry_roll5": 3.6,
        "heat_roll10": 99.7,
        "muggy_roll10": 69.0,
        "rain_roll10": 27.2,
        "snow_roll10": 0.0,
        "mosquito_roll10": 363.2,
        "dry_roll10": 4.1,
        "heat_trend": 105.3,
        "muggy_trend": 81.8,
        "rain_trend": 27.2,
        "snow_trend": 0.0,
        "mosquito_trend": 359.1,
        "dry_trend": 4.3,
        "springFrost": 0,
        "fallFrost": 0
      },
      "2047": {
        "heat": 106,
        "muggy": 93,
        "rain": 38,
        "snow": 0,
        "mosquito": 354,
        "dry": 7,
        "heat_roll5": 102.2,
        "muggy_roll5": 71.6,
        "rain_roll5": 32.0,
        "snow_roll5": 0.0,
        "mosquito_roll5": 366.6,
        "dry_roll5": 4.0,
        "heat_roll10": 102.1,
        "muggy_roll10": 73.3,
        "rain_roll10": 28.8,
        "snow_roll10": 0.0,
        "mosquito_roll10": 361.4,
        "dry_roll10": 4.1,
        "heat_trend": 106.5,
        "muggy_trend": 81.6,
        "rain_trend": 27.2,
        "snow_trend": 0.0,
        "mosquito_trend": 359.0,
        "dry_trend": 4.0,
        "springFrost": 0,
        "fallFrost": 0
      },
      "2048": {
        "heat": 84,
        "muggy": 106,
        "rain": 20,
        "snow": 0,
        "mosquito": 339,
        "dry": 6,
        "heat_roll5": 95.8,
        "muggy_roll5": 77.6,
        "rain_roll5": 29.2,
        "snow_roll5": 0.0,
        "mosquito_roll5": 359.8,
        "dry_roll5": 4.4,
        "heat_roll10": 103.1,
        "muggy_roll10": 78.6,
        "rain_roll10": 30.0,
        "snow_roll10": 0.0,
        "mosquito_roll10": 359.5,
        "dry_roll10": 4.0,
        "heat_trend": 107.6,
        "muggy_trend": 81.4,
        "rain_trend": 27.1,
        "snow_trend": 0.0,
        "mosquito_trend": 358.8,
        "dry_trend": 3.7,
        "springFrost": 0,
        "fallFrost": 0
      },
      "2049": {
        "heat": 97,
        "muggy": 95,
        "rain": 20,
        "snow": 0,
        "mosquito": 354,
        "dry": 4,
        "heat_roll5": 94.0,
        "muggy_roll5": 80.8,
        "rain_roll5": 26.0,
        "snow_roll5": 0.0,
        "mosquito_roll5": 352.6,
        "dry_roll5": 5.2,
        "heat_roll10": 101.4,
        "muggy_roll10": 79.8,
        "rain_roll10": 29.2,
        "snow_roll10": 0.0,
        "mosquito_roll10": 358.5,
        "dry_roll10": 4.1,
        "heat_trend": 108.6,
        "muggy_trend": 81.0,
        "rain_trend": 26.9,
        "snow_trend": 0.0,
        "mosquito_trend": 358.6,
        "dry_trend": 3.4,
        "springFrost": 0,
        "fallFrost": 0
      },
      "2050": {
        "heat": 141,
        "muggy": 78,
        "rain": 26,
        "snow": 0,
        "mosquito": 367,
        "dry": 2,
        "heat_roll5": 104.2,
        "muggy_roll5": 86.2,
        "rain_roll5": 28.4,
        "snow_roll5": 0.0,
        "mosquito_roll5": 356.2,
        "dry_roll5": 4.4,
        "heat_roll10": 105.0,
        "muggy_roll10": 81.9,
        "rain_roll10": 28.0,
        "snow_roll10": 0.0,
        "mosquito_roll10": 358.3,
        "dry_roll10": 3.8,
        "heat_trend": 109.6,
        "muggy_trend": 80.5,
        "rain_trend": 26.8,
        "snow_trend": 0.0,
        "mosquito_trend": 358.3,
        "dry_trend": 3.0,
        "springFrost": 0,
        "fallFrost": 0
      }
    },
    "ssp245": {
      "2026": {
        "heat": 86,
        "muggy": 47,
        "rain": 18,
        "snow": 0,
        "mosquito": 348,
        "dry": 4,
        "heat_roll5": 76.8,
        "muggy_roll5": 64.8,
        "rain_roll5": 21.4,
        "snow_roll5": 0.0,
        "mosquito_roll5": 341.0,
        "dry_roll5": 5.8,
        "heat_roll10": 63.3,
        "muggy_roll10": 56.9,
        "rain_roll10": 25.2,
        "snow_roll10": 0.0,
        "mosquito_roll10": 345.9,
        "dry_roll10": 6.5,
        "heat_trend": 69.4,
        "muggy_trend": 60.9,
        "rain_trend": 22.5,
        "snow_trend": 0.0,
        "mosquito_trend": 343.1,
        "dry_trend": 6.9,
        "springFrost": 0,
        "fallFrost": 0
      },
      "2027": {
        "heat": 91,
        "muggy": 59,
        "rain": 40,
        "snow": 0,
        "mosquito": 358,
        "dry": 4,
        "heat_roll5": 91.6,
        "muggy_roll5": 72.6,
        "rain_roll5": 25.8,
        "snow_roll5": 0.0,
        "mosquito_roll5": 340.6,
        "dry_roll5": 6.0,
        "heat_roll10": 67.3,
        "muggy_roll10": 57.9,
        "rain_roll10": 25.1,
        "snow_roll10": 0.0,
        "mosquito_roll10": 346.5,
        "dry_roll10": 6.1,
        "heat_trend": 73.7,
        "muggy_trend": 61.2,
        "rain_trend": 23.1,
        "snow_trend": 0.0,
        "mosquito_trend": 345.6,
        "dry_trend": 6.6,
        "springFrost": 0,
        "fallFrost": 0
      },
      "2028": {
        "heat": 91,
        "muggy": 56,
        "rain": 20,
        "snow": 0,
        "mosquito": 340,
        "dry": 16,
        "heat_roll5": 94.8,
        "muggy_roll5": 69.4,
        "rain_roll5": 25.6,
        "snow_roll5": 0.0,
        "mosquito_roll5": 339.8,
        "dry_roll5": 7.8,
        "heat_roll10": 72.2,
        "muggy_roll10": 59.5,
        "rain_roll10": 24.6,
        "snow_roll10": 0.0,
        "mosquito_roll10": 345.9,
        "dry_roll10": 6.9,
        "heat_trend": 77.9,
        "muggy_trend": 61.7,
        "rain_trend": 23.7,
        "snow_trend": 0.0,
        "mosquito_trend": 348.0,
        "dry_trend": 6.3,
        "springFrost": 0,
        "fallFrost": 0
      },
      "2029": {
        "heat": 89,
        "muggy": 77,
        "rain": 14,
        "snow": 0,
        "mosquito": 327,
        "dry": 16,
        "heat_roll5": 83.8,
        "muggy_roll5": 57.8,
        "rain_roll5": 23.6,
        "snow_roll5": 0.0,
        "mosquito_roll5": 336.2,
        "dry_roll5": 9.0,
        "heat_roll10": 74.5,
        "muggy_roll10": 60.9,
        "rain_roll10": 23.1,
        "snow_roll10": 0.0,
        "mosquito_roll10": 342.3,
        "dry_roll10": 8.2,
        "heat_trend": 81.9,
        "muggy_trend": 62.5,
        "rain_trend": 24.3,
        "snow_trend": 0.0,
        "mosquito_trend": 350.2,
        "dry_trend": 6.1,
        "springFrost": 0,
        "fallFrost": 0
      },
      "2030": {
        "heat": 73,
        "muggy": 96,
        "rain": 22,
        "snow": 0,
        "mosquito": 354,
        "dry": 3,
        "heat_roll5": 86.0,
        "muggy_roll5": 67.0,
        "rain_roll5": 22.8,
        "snow_roll5": 0.0,
        "mosquito_roll5": 345.4,
        "dry_roll5": 8.6,
        "heat_roll10": 75.4,
        "muggy_roll10": 63.9,
        "rain_roll10": 22.3,
        "snow_roll10": 0.0,
        "mosquito_roll10": 342.9,
        "dry_roll10": 7.9,
        "heat_trend": 85.7,
        "muggy_trend": 63.5,
        "rain_trend": 24.8,
        "snow_trend": 0.0,
        "mosquito_trend": 352.2,
        "dry_trend": 5.8,
        "springFrost": 0,
        "fallFrost": 0
      },
      "2031": {
        "heat": 76,
        "muggy": 88,
        "rain": 14,
        "snow": 0,
        "mosquito": 319,
        "dry": 10,
        "heat_roll5": 84.0,
        "muggy_roll5": 75.2,
        "rain_roll5": 22.0,
        "snow_roll5": 0.0,
        "mosquito_roll5": 339.6,
        "dry_roll5": 9.8,
        "heat_roll10": 80.4,
        "muggy_roll10": 70.0,
        "rain_roll10": 21.7,
        "snow_roll10": 0.0,
        "mosquito_roll10": 340.3,
        "dry_roll10": 7.8,
        "heat_trend": 89.3,
        "muggy_trend": 64.7,
        "rain_trend": 25.3,
        "snow_trend": 0.0,
        "mosquito_trend": 354.1,
        "dry_trend": 5.6,
        "springFrost": 0,
        "fallFrost": 0
      },
      "2032": {
        "heat": 91,
        "muggy": 74,
        "rain": 26,
        "snow": 0,
        "mosquito": 367,
        "dry": 2,
        "heat_roll5": 84.0,
        "muggy_roll5": 78.2,
        "rain_roll5": 19.2,
        "snow_roll5": 0.0,
        "mosquito_roll5": 341.4,
        "dry_roll5": 9.4,
        "heat_roll10": 87.8,
        "muggy_roll10": 75.4,
        "rain_roll10": 22.5,
        "snow_roll10": 0.0,
        "mosquito_roll10": 341.0,
        "dry_roll10": 7.7,
        "heat_trend": 92.7,
        "muggy_trend": 66.2,
        "rain_trend": 25.7,
        "snow_trend": 0.0,
        "mosquito_trend": 355.8,
        "dry_trend": 5.4,
        "springFrost": 0,
        "fallFrost": 0
      },
      "2033": {
        "heat": 78,
        "muggy": 54,
        "rain": 34,
        "snow": 0,
        "mosquito": 356,
        "dry": 10,
        "heat_roll5": 81.4,
        "muggy_roll5": 77.8,
        "rain_roll5": 22.0,
        "snow_roll5": 0.0,
        "mosquito_roll5": 344.6,
        "dry_roll5": 8.2,
        "heat_roll10": 88.1,
        "muggy_roll10": 73.6,
        "rain_roll10": 23.8,
        "snow_roll10": 0.0,
        "mosquito_roll10": 342.2,
        "dry_roll10": 8.0,
        "heat_trend": 95.9,
        "muggy_trend": 67.9,
        "rain_trend": 26.1,
        "snow_trend": 0.0,
        "mosquito_trend": 357.4,
        "dry_trend": 5.2,
        "springFrost": 0,
        "fallFrost": 0
      },
      "2034": {
        "heat": 92,
        "muggy": 47,
        "rain": 18,
        "snow": 0,
        "mosquito": 356,
        "dry": 2,
        "heat_roll5": 82.0,
        "muggy_roll5": 71.8,
        "rain_roll5": 22.8,
        "snow_roll5": 0.0,
        "mosquito_roll5": 350.4,
        "dry_roll5": 5.4,
        "heat_roll10": 82.9,
        "muggy_roll10": 64.8,
        "rain_roll10": 23.2,
        "snow_roll10": 0.0,
        "mosquito_roll10": 343.3,
        "dry_roll10": 7.2,
        "heat_trend": 98.9,
        "muggy_trend": 69.8,
        "rain_trend": 26.4,
        "snow_trend": 0.0,
        "mosquito_trend": 358.8,
        "dry_trend": 5.0,
        "springFrost": 0,
        "fallFrost": 0
      },
      "2035": {
        "heat": 93,
        "muggy": 76,
        "rain": 28,
        "snow": 0,
        "mosquito": 370,
        "dry": 8,
        "heat_roll5": 86.0,
        "muggy_roll5": 67.8,
        "rain_roll5": 24.0,
        "snow_roll5": 0.0,
        "mosquito_roll5": 353.6,
        "dry_roll5": 6.4,
        "heat_roll10": 86.0,
        "muggy_roll10": 67.4,
        "rain_roll10": 23.4,
        "snow_roll10": 0.0,
        "mosquito_roll10": 349.5,
        "dry_roll10": 7.5,
        "heat_trend": 101.7,
        "muggy_trend": 71.9,
        "rain_trend": 26.7,
        "snow_trend": 0.0,
        "mosquito_trend": 360.0,
        "dry_trend": 4.9,
        "springFrost": 0,
        "fallFrost": 0
      },
      "2036": {
        "heat": 92,
        "muggy": 60,
        "rain": 34,
        "snow": 0,
        "mosquito": 372,
        "dry": 3,
        "heat_roll5": 89.2,
        "muggy_roll5": 62.2,
        "rain_roll5": 28.0,
        "snow_roll5": 0.0,
        "mosquito_roll5": 364.2,
        "dry_roll5": 5.0,
        "heat_roll10": 86.6,
        "muggy_roll10": 68.7,
        "rain_roll10": 25.0,
        "snow_roll10": 0.0,
        "mosquito_roll10": 351.9,
        "dry_roll10": 7.4,
        "heat_trend": 104.4,
        "muggy_trend": 74.3,
        "rain_trend": 27.0,
        "snow_trend": 0.0,
        "mosquito_trend": 361.1,
        "dry_trend": 4.7,
        "springFrost": 0,
        "fallFrost": 0
      },
      "2037": {
        "heat": 101,
        "muggy": 70,
        "rain": 36,
        "snow": 0,
        "mosquito": 367,
        "dry": 1,
        "heat_roll5": 91.2,
        "muggy_roll5": 61.4,
        "rain_roll5": 30.0,
        "snow_roll5": 0.0,
        "mosquito_roll5": 364.2,
        "dry_roll5": 4.8,
        "heat_roll10": 87.6,
        "muggy_roll10": 69.8,
        "rain_roll10": 24.6,
        "snow_roll10": 0.0,
        "mosquito_roll10": 352.8,
        "dry_roll10": 7.1,
        "heat_trend": 106.8,
        "muggy_trend": 76.9,
        "rain_trend": 27.2,
        "snow_trend": 0.0,
        "mosquito_trend": 362.0,
        "dry_trend": 4.6,
        "springFrost": 0,
        "fallFrost": 0
      },
      "2038": {
        "heat": 119,
        "muggy": 72,
        "rain": 32,
        "snow": 0,
        "mosquito": 373,
        "dry": 5,
        "heat_roll5": 99.4,
        "muggy_roll5": 65.0,
        "rain_roll5": 29.6,
        "snow_roll5": 0.0,
        "mosquito_roll5": 367.6,
        "dry_roll5": 3.8,
        "heat_roll10": 90.4,
        "muggy_roll10": 71.4,
        "rain_roll10": 25.8,
        "snow_roll10": 0.0,
        "mosquito_roll10": 356.1,
        "dry_roll10": 6.0,
        "heat_trend": 109.1,
        "muggy_trend": 79.7,
        "rain_trend": 27.3,
        "snow_trend": 0.0,
        "mosquito_trend": 362.8,
        "dry_trend": 4.5,
        "springFrost": 0,
        "fallFrost": 0
      },
      "2039": {
        "heat": 139,
        "muggy": 70,
        "rain": 26,
        "snow": 0,
        "mosquito": 369,
        "dry": 0,
        "heat_roll5": 108.8,
        "muggy_roll5": 69.6,
        "rain_roll5": 31.2,
        "snow_roll5": 0.0,
        "mosquito_roll5": 370.2,
        "dry_roll5": 3.4,
        "heat_roll10": 95.4,
        "muggy_roll10": 70.7,
        "rain_roll10": 27.0,
        "snow_roll10": 0.0,
        "mosquito_roll10": 360.3,
        "dry_roll10": 4.4,
        "heat_trend": 111.2,
        "muggy_trend": 82.8,
        "rain_trend": 27.4,
        "snow_trend": 0.0,
        "mosquito_trend": 363.4,
        "dry_trend": 4.5,
        "springFrost": 0,
        "fallFrost": 0
      },
      "2040": {
        "heat": 115,
        "muggy": 96,
        "rain": 24,
        "snow": 0,
        "mosquito": 367,
        "dry": 4,
        "heat_roll5": 113.2,
        "muggy_roll5": 73.6,
        "rain_roll5": 30.4,
        "snow_roll5": 0.0,
        "mosquito_roll5": 369.6,
        "dry_roll5": 2.6,
        "heat_roll10": 99.6,
        "muggy_roll10": 70.7,
        "rain_roll10": 27.2,
        "snow_roll10": 0.0,
        "mosquito_roll10": 361.6,
        "dry_roll10": 4.5,
        "heat_trend": 113.0,
        "muggy_trend": 86.1,
        "rain_trend": 27.5,
        "snow_trend": 0.0,
        "mosquito_trend": 363.8,
        "dry_trend": 4.4,
        "springFrost": 0,
        "fallFrost": 0
      },
      "2041": {
        "heat": 89,
        "muggy": 127,
        "rain": 22,
        "snow": 0,
        "mosquito": 320,
        "dry": 12,
        "heat_roll5": 112.6,
        "muggy_roll5": 87.0,
        "rain_roll5": 28.0,
        "snow_roll5": 0.0,
        "mosquito_roll5": 359.2,
        "dry_roll5": 4.4,
        "heat_roll10": 100.9,
        "muggy_roll10": 74.6,
        "rain_roll10": 28.0,
        "snow_roll10": 0.0,
        "mosquito_roll10": 361.7,
        "dry_roll10": 4.7,
        "heat_trend": 114.7,
        "muggy_trend": 89.6,
        "rain_trend": 27.5,
        "snow_trend": 0.0,
        "mosquito_trend": 364.1,
        "dry_trend": 4.4,
        "springFrost": 0,
        "fallFrost": 0
      },
      "2042": {
        "heat": 117,
        "muggy": 132,
        "rain": 30,
        "snow": 0,
        "mosquito": 344,
        "dry": 8,
        "heat_roll5": 115.8,
        "muggy_roll5": 99.4,
        "rain_roll5": 26.8,
        "snow_roll5": 0.0,
        "mosquito_roll5": 354.6,
        "dry_roll5": 5.8,
        "heat_roll10": 103.5,
        "muggy_roll10": 80.4,
        "rain_roll10": 28.4,
        "snow_roll10": 0.0,
        "mosquito_roll10": 359.4,
        "dry_roll10": 5.3,
        "heat_trend": 116.2,
        "muggy_trend": 93.3,
        "rain_trend": 27.5,
        "snow_trend": 0.0,
        "mosquito_trend": 364.2,
        "dry_trend": 4.3,
        "springFrost": 0,
        "fallFrost": 0
      },
      "2043": {
        "heat": 135,
        "muggy": 87,
        "rain": 34,
        "snow": 0,
        "mosquito": 385,
        "dry": 0,
        "heat_roll5": 119.0,
        "muggy_roll5": 102.4,
        "rain_roll5": 27.2,
        "snow_roll5": 0.0,
        "mosquito_roll5": 357.0,
        "dry_roll5": 4.8,
        "heat_roll10": 109.2,
        "muggy_roll10": 83.7,
        "rain_roll10": 28.4,
        "snow_roll10": 0.0,
        "mosquito_roll10": 362.3,
        "dry_roll10": 4.3,
        "heat_trend": 117.5,
        "muggy_trend": 97.3,
        "rain_trend": 27.5,
        "snow_trend": 0.0,
        "mosquito_trend": 364.2,
        "dry_trend": 4.3,
        "springFrost": 0,
        "fallFrost": 0
      },
      "2044": {
        "heat": 140,
        "muggy": 75,
        "rain": 28,
        "snow": 0,
        "mosquito": 391,
        "dry": 0,
        "heat_roll5": 119.2,
        "muggy_roll5": 103.4,
        "rain_roll5": 27.6,
        "snow_roll5": 0.0,
        "mosquito_roll5": 361.4,
        "dry_roll5": 4.8,
        "heat_roll10": 114.0,
        "muggy_roll10": 86.5,
        "rain_roll10": 29.4,
        "snow_roll10": 0.0,
        "mosquito_roll10": 365.8,
        "dry_roll10": 4.1,
        "heat_trend": 118.6,
        "muggy_trend": 101.5,
        "rain_trend": 27.4,
        "snow_trend": 0.0,
        "mosquito_trend": 364.0,
        "dry_trend": 4.3,
        "springFrost": 0,
        "fallFrost": 0
      },
      "2045": {
        "heat": 98,
        "muggy": 72,
        "rain": 34,
        "snow": 0,
        "mosquito": 361,
        "dry": 3,
        "heat_roll5": 115.8,
        "muggy_roll5": 98.6,
        "rain_roll5": 29.6,
        "snow_roll5": 0.0,
        "mosquito_roll5": 360.2,
        "dry_roll5": 4.6,
        "heat_roll10": 114.5,
        "muggy_roll10": 86.1,
        "rain_roll10": 30.0,
        "snow_roll10": 0.0,
        "mosquito_roll10": 364.9,
        "dry_roll10": 3.6,
        "heat_trend": 119.5,
        "muggy_trend": 105.9,
        "rain_trend": 27.2,
        "snow_trend": 0.0,
        "mosquito_trend": 363.6,
        "dry_trend": 4.4,
        "springFrost": 0,
        "fallFrost": 0
      },
      "2046": {
        "heat": 142,
        "muggy": 84,
        "rain": 18,
        "snow": 0,
        "mosquito": 379,
        "dry": 0,
        "heat_roll5": 126.4,
        "muggy_roll5": 90.0,
        "rain_roll5": 28.8,
        "snow_roll5": 0.0,
        "mosquito_roll5": 372.0,
        "dry_roll5": 2.2,
        "heat_roll10": 119.5,
        "muggy_roll10": 88.5,
        "rain_roll10": 28.4,
        "snow_roll10": 0.0,
        "mosquito_roll10": 365.6,
        "dry_roll10": 3.3,
        "heat_trend": 120.3,
        "muggy_trend": 110.5,
        "rain_trend": 27.1,
        "snow_trend": 0.0,
        "mosquito_trend": 363.1,
        "dry_trend": 4.4,
        "springFrost": 0,
        "fallFrost": 0
      },
      "2047": {
        "heat": 118,
        "muggy": 93,
        "rain": 14,
        "snow": 0,
        "mosquito": 377,
        "dry": 0,
        "heat_roll5": 126.6,
        "muggy_roll5": 82.2,
        "rain_roll5": 25.6,
        "snow_roll5": 0.0,
        "mosquito_roll5": 378.6,
        "dry_roll5": 0.6,
        "heat_roll10": 121.2,
        "muggy_roll10": 90.8,
        "rain_roll10": 26.2,
        "snow_roll10": 0.0,
        "mosquito_roll10": 366.6,
        "dry_roll10": 3.2,
        "heat_trend": 120.8,
        "muggy_trend": 115.4,
        "rain_trend": 26.8,
        "snow_trend": 0.0,
        "mosquito_trend": 362.4,
        "dry_trend": 4.5,
        "springFrost": 0,
        "fallFrost": 0
      },
      "2048": {
        "heat": 163,
        "muggy": 180,
        "rain": 28,
        "snow": 0,
        "mosquito": 354,
        "dry": 4,
        "heat_roll5": 132.2,
        "muggy_roll5": 100.8,
        "rain_roll5": 24.4,
        "snow_roll5": 0.0,
        "mosquito_roll5": 372.4,
        "dry_roll5": 1.4,
        "heat_roll10": 125.6,
        "muggy_roll10": 101.6,
        "rain_roll10": 25.8,
        "snow_roll10": 0.0,
        "mosquito_roll10": 364.7,
        "dry_roll10": 3.1,
        "heat_trend": 121.2,
        "muggy_trend": 120.5,
        "rain_trend": 26.5,
        "snow_trend": 0.0,
        "mosquito_trend": 361.6,
        "dry_trend": 4.6,
        "springFrost": 0,
        "fallFrost": 0
      },
      "2049": {
        "heat": 93,
        "muggy": 136,
        "rain": 22,
        "snow": 0,
        "mosquito": 344,
        "dry": 5,
        "heat_roll5": 122.8,
        "muggy_roll5": 113.0,
        "rain_roll5": 23.2,
        "snow_roll5": 0.0,
        "mosquito_roll5": 363.0,
        "dry_roll5": 2.4,
        "heat_roll10": 121.0,
        "muggy_roll10": 108.2,
        "rain_roll10": 25.4,
        "snow_roll10": 0.0,
        "mosquito_roll10": 362.2,
        "dry_roll10": 3.6,
        "heat_trend": 121.3,
        "muggy_trend": 125.9,
        "rain_trend": 26.2,
        "snow_trend": 0.0,
        "mosquito_trend": 360.6,
        "dry_trend": 4.7,
        "springFrost": 0,
        "fallFrost": 0
      },
      "2050": {
        "heat": 98,
        "muggy": 124,
        "rain": 36,
        "snow": 0,
        "mosquito": 353,
        "dry": 14,
        "heat_roll5": 122.8,
        "muggy_roll5": 123.4,
        "rain_roll5": 23.6,
        "snow_roll5": 0.0,
        "mosquito_roll5": 361.4,
        "dry_roll5": 4.6,
        "heat_roll10": 119.3,
        "muggy_roll10": 111.0,
        "rain_roll10": 26.6,
        "snow_roll10": 0.0,
        "mosquito_roll10": 360.8,
        "dry_roll10": 4.6,
        "heat_trend": 121.3,
        "muggy_trend": 131.4,
        "rain_trend": 25.9,
        "snow_trend": 0.0,
        "mosquito_trend": 359.4,
        "dry_trend": 4.8,
        "springFrost": 0,
        "fallFrost": 0
      }
    },
    "ssp585": {
      "2026": {
        "heat": 71,
        "muggy": 37,
        "rain": 22,
        "snow": 0,
        "mosquito": 347,
        "dry": 12,
        "heat_roll5": 73.8,
        "muggy_roll5": 62.8,
        "rain_roll5": 22.2,
        "snow_roll5": 0.0,
        "mosquito_roll5": 340.8,
        "dry_roll5": 7.4,
        "heat_roll10": 61.8,
        "muggy_roll10": 55.9,
        "rain_roll10": 25.6,
        "snow_roll10": 0.0,
        "mosquito_roll10": 345.8,
        "dry_roll10": 7.3,
        "heat_trend": 70.5,
        "muggy_trend": 63.2,
        "rain_trend": 22.7,
        "snow_trend": 0.0,
        "mosquito_trend": 343.8,
        "dry_trend": 6.7,
        "springFrost": 0,
        "fallFrost": 0
      },
      "2027": {
        "heat": 144,
        "muggy": 118,
        "rain": 28,
        "snow": 0,
        "mosquito": 378,
        "dry": 1,
        "heat_roll5": 99.2,
        "muggy_roll5": 82.4,
        "rain_roll5": 24.2,
        "snow_roll5": 0.0,
        "mosquito_roll5": 344.4,
        "dry_roll5": 7.0,
        "heat_roll10": 71.1,
        "muggy_roll10": 62.8,
        "rain_roll10": 24.3,
        "snow_roll10": 0.0,
        "mosquito_roll10": 348.4,
        "dry_roll10": 6.6,
        "heat_trend": 76.0,
        "muggy_trend": 65.7,
        "rain_trend": 23.4,
        "snow_trend": 0.0,
        "mosquito_trend": 346.9,
        "dry_trend": 6.2,
        "springFrost": 0,
        "fallFrost": 0
      },
      "2028": {
        "heat": 110,
        "muggy": 132,
        "rain": 26,
        "snow": 0,
        "mosquito": 327,
        "dry": 12,
        "heat_roll5": 106.2,
        "muggy_roll5": 94.4,
        "rain_roll5": 25.2,
        "snow_roll5": 0.0,
        "mosquito_roll5": 341.0,
        "dry_roll5": 8.0,
        "heat_roll10": 77.9,
        "muggy_roll10": 72.0,
        "rain_roll10": 24.4,
        "snow_roll10": 0.0,
        "mosquito_roll10": 346.5,
        "dry_roll10": 7.0,
        "heat_trend": 81.2,
        "muggy_trend": 68.4,
        "rain_trend": 24.1,
        "snow_trend": 0.0,
        "mosquito_trend": 349.6,
        "dry_trend": 5.7,
        "springFrost": 0,
        "fallFrost": 0
      },
      "2029": {
        "heat": 74,
        "muggy": 65,
        "rain": 26,
        "snow": 0,
        "mosquito": 371,
        "dry": 1,
        "heat_roll5": 92.2,
        "muggy_roll5": 80.4,
        "rain_roll5": 25.6,
        "snow_roll5": 0.0,
        "mosquito_roll5": 346.2,
        "dry_roll5": 6.2,
        "heat_roll10": 78.7,
        "muggy_roll10": 72.2,
        "rain_roll10": 24.1,
        "snow_roll10": 0.0,
        "mosquito_roll10": 347.3,
        "dry_roll10": 6.8,
        "heat_trend": 86.2,
        "muggy_trend": 71.1,
        "rain_trend": 24.8,
        "snow_trend": 0.0,
        "mosquito_trend": 352.1,
        "dry_trend": 5.3,
        "springFrost": 0,
        "fallFrost": 0
      },
      "2030": {
        "heat": 63,
        "muggy": 47,
        "rain": 34,
        "snow": 0,
        "mosquito": 340,
        "dry": 10,
        "heat_roll5": 92.4,
        "muggy_roll5": 79.8,
        "rain_roll5": 27.2,
        "snow_roll5": 0.0,
        "mosquito_roll5": 352.6,
        "dry_roll5": 7.2,
        "heat_roll10": 78.6,
        "muggy_roll10": 70.3,
        "rain_roll10": 24.5,
        "snow_roll10": 0.0,
        "mosquito_roll10": 346.5,
        "dry_roll10": 7.2,
        "heat_trend": 91.0,
        "muggy_trend": 74.0,
        "rain_trend": 25.3,
        "snow_trend": 0.0,
        "mosquito_trend": 354.3,
        "dry_trend": 4.9,
        "springFrost": 0,
        "fallFrost": 0
      },
      "2031": {
        "heat": 107,
        "muggy": 97,
        "rain": 18,
        "snow": 0,
        "mosquito": 352,
        "dry": 6,
        "heat_roll5": 99.6,
        "muggy_roll5": 91.8,
        "rain_roll5": 26.4,
        "snow_roll5": 0.0,
        "mosquito_roll5": 353.6,
        "dry_roll5": 6.0,
        "heat_roll10": 86.7,
        "muggy_roll10": 77.3,
        "rain_roll10": 24.3,
        "snow_roll10": 0.0,
        "mosquito_roll10": 347.2,
        "dry_roll10": 6.7,
        "heat_trend": 95.5,
        "muggy_trend": 77.0,
        "rain_trend": 25.8,
        "snow_trend": 0.0,
        "mosquito_trend": 356.2,
        "dry_trend": 4.6,
        "springFrost": 0,
        "fallFrost": 0
      },
      "2032": {
        "heat": 168,
        "muggy": 118,
        "rain": 38,
        "snow": 0,
        "mosquito": 379,
        "dry": 1,
        "heat_roll5": 104.4,
        "muggy_roll5": 91.8,
        "rain_roll5": 28.4,
        "snow_roll5": 0.0,
        "mosquito_roll5": 353.8,
        "dry_roll5": 6.0,
        "heat_roll10": 101.8,
        "muggy_roll10": 87.1,
        "rain_roll10": 26.3,
        "snow_roll10": 0.0,
        "mosquito_roll10": 349.1,
        "dry_roll10": 6.5,
        "heat_trend": 99.8,
        "muggy_trend": 80.2,
        "rain_trend": 26.2,
        "snow_trend": 0.0,
        "mosquito_trend": 357.8,
        "dry_trend": 4.3,
        "springFrost": 0,
        "fallFrost": 0
      },
      "2033": {
        "heat": 83,
        "muggy": 58,
        "rain": 20,
        "snow": 0,
        "mosquito": 376,
        "dry": 2,
        "heat_roll5": 99.0,
        "muggy_roll5": 77.0,
        "rain_roll5": 27.2,
        "snow_roll5": 0.0,
        "mosquito_roll5": 363.6,
        "dry_roll5": 4.0,
        "heat_roll10": 102.6,
        "muggy_roll10": 85.7,
        "rain_roll10": 26.2,
        "snow_roll10": 0.0,
        "mosquito_roll10": 352.3,
        "dry_roll10": 6.0,
        "heat_trend": 103.9,
        "muggy_trend": 83.5,
        "rain_trend": 26.6,
        "snow_trend": 0.0,
        "mosquito_trend": 359.1,
        "dry_trend": 4.0,
        "springFrost": 0,
        "fallFrost": 0
      },
      "2034": {
        "heat": 90,
        "muggy": 72,
        "rain": 34,
        "snow": 0,
        "mosquito": 376,
        "dry": 0,
        "heat_roll5": 102.2,
        "muggy_roll5": 78.4,
        "rain_roll5": 28.8,
        "snow_roll5": 0.0,
        "mosquito_roll5": 364.6,
        "dry_roll5": 3.8,
        "heat_roll10": 97.2,
        "muggy_roll10": 79.4,
        "rain_roll10": 27.2,
        "snow_roll10": 0.0,
        "mosquito_roll10": 355.4,
        "dry_roll10": 5.0,
        "heat_trend": 107.7,
        "muggy_trend": 86.8,
        "rain_trend": 26.9,
        "snow_trend": 0.0,
        "mosquito_trend": 360.1,
        "dry_trend": 3.8,
        "springFrost": 0,
        "fallFrost": 0
      },
      "2035": {
        "heat": 99,
        "muggy": 69,
        "rain": 24,
        "snow": 0,
        "mosquito": 354,
        "dry": 6,
        "heat_roll5": 109.4,
        "muggy_roll5": 82.8,
        "rain_roll5": 26.8,
        "snow_roll5": 0.0,
        "mosquito_roll5": 367.4,
        "dry_roll5": 3.0,
        "heat_roll10": 100.9,
        "muggy_roll10": 81.3,
        "rain_roll10": 27.0,
        "snow_roll10": 0.0,
        "mosquito_roll10": 360.0,
        "dry_roll10": 5.1,
        "heat_trend": 111.3,
        "muggy_trend": 90.4,
        "rain_trend": 27.1,
        "snow_trend": 0.0,
        "mosquito_trend": 360.8,
        "dry_trend": 3.6,
        "springFrost": 0,
        "fallFrost": 0
      },
      "2036": {
        "heat": 106,
        "muggy": 65,
        "rain": 38,
        "snow": 0,
        "mosquito": 375,
        "dry": 0,
        "heat_roll5": 109.2,
        "muggy_roll5": 76.4,
        "rain_roll5": 30.8,
        "snow_roll5": 0.0,
        "mosquito_roll5": 372.0,
        "dry_roll5": 1.8,
        "heat_roll10": 104.4,
        "muggy_roll10": 84.1,
        "rain_roll10": 28.6,
        "snow_roll10": 0.0,
        "mosquito_roll10": 362.8,
        "dry_roll10": 3.9,
        "heat_trend": 114.7,
        "muggy_trend": 94.0,
        "rain_trend": 27.2,
        "snow_trend": 0.0,
        "mosquito_trend": 361.3,
        "dry_trend": 3.5,
        "springFrost": 0,
        "fallFrost": 0
      },
      "2037": {
        "heat": 133,
        "muggy": 103,
        "rain": 32,
        "snow": 0,
        "mosquito": 378,
        "dry": 2,
        "heat_roll5": 102.2,
        "muggy_roll5": 73.4,
        "rain_roll5": 29.6,
        "snow_roll5": 0.0,
        "mosquito_roll5": 371.8,
        "dry_roll5": 2.0,
        "heat_roll10": 103.3,
        "muggy_roll10": 82.6,
        "rain_roll10": 29.0,
        "snow_roll10": 0.0,
        "mosquito_roll10": 362.8,
        "dry_roll10": 4.0,
        "heat_trend": 117.8,
        "muggy_trend": 97.8,
        "rain_trend": 27.2,
        "snow_trend": 0.0,
        "mosquito_trend": 361.4,
        "dry_trend": 3.3,
        "springFrost": 0,
        "fallFrost": 0
      },
      "2038": {
        "heat": 136,
        "muggy": 101,
        "rain": 12,
        "snow": 0,
        "mosquito": 358,
        "dry": 4,
        "heat_roll5": 112.8,
        "muggy_roll5": 82.0,
        "rain_roll5": 28.0,
        "snow_roll5": 0.0,
        "mosquito_roll5": 368.2,
        "dry_roll5": 2.4,
        "heat_roll10": 105.9,
        "muggy_roll10": 79.5,
        "rain_roll10": 27.6,
        "snow_roll10": 0.0,
        "mosquito_roll10": 365.9,
        "dry_roll10": 3.2,
        "heat_trend": 120.7,
        "muggy_trend": 101.7,
        "rain_trend": 27.2,
        "snow_trend": 0.0,
        "mosquito_trend": 361.2,
        "dry_trend": 3.3,
        "springFrost": 0,
        "fallFrost": 0
      },
      "2039": {
        "heat": 111,
        "muggy": 83,
        "rain": 30,
        "snow": 0,
        "mosquito": 359,
        "dry": 4,
        "heat_roll5": 117.0,
        "muggy_roll5": 84.2,
        "rain_roll5": 27.2,
        "snow_roll5": 0.0,
        "mosquito_roll5": 364.8,
        "dry_roll5": 3.2,
        "heat_roll10": 109.6,
        "muggy_roll10": 81.3,
        "rain_roll10": 28.0,
        "snow_roll10": 0.0,
        "mosquito_roll10": 364.7,
        "dry_roll10": 3.5,
        "heat_trend": 123.4,
        "muggy_trend": 105.7,
        "rain_trend": 27.1,
        "snow_trend": 0.0,
        "mosquito_trend": 360.7,
        "dry_trend": 3.2,
        "springFrost": 0,
        "fallFrost": 0
      },
      "2040": {
        "heat": 117,
        "muggy": 126,
        "rain": 10,
        "snow": 0,
        "mosquito": 328,
        "dry": 8,
        "heat_roll5": 120.6,
        "muggy_roll5": 95.6,
        "rain_roll5": 24.4,
        "snow_roll5": 0.0,
        "mosquito_roll5": 359.6,
        "dry_roll5": 3.6,
        "heat_roll10": 115.0,
        "muggy_roll10": 89.2,
        "rain_roll10": 25.6,
        "snow_roll10": 0.0,
        "mosquito_roll10": 363.5,
        "dry_roll10": 3.3,
        "heat_trend": 125.8,
        "muggy_trend": 109.8,
        "rain_trend": 27.0,
        "snow_trend": 0.0,
        "mosquito_trend": 360.0,
        "dry_trend": 3.2,
        "springFrost": 0,
        "fallFrost": 0
      },
      "2041": {
        "heat": 155,
        "muggy": 151,
        "rain": 24,
        "snow": 0,
        "mosquito": 369,
        "dry": 2,
        "heat_roll5": 130.4,
        "muggy_roll5": 112.8,
        "rain_roll5": 21.6,
        "snow_roll5": 0.0,
        "mosquito_roll5": 358.4,
        "dry_roll5": 4.0,
        "heat_roll10": 119.8,
        "muggy_roll10": 94.6,
        "rain_roll10": 26.2,
        "snow_roll10": 0.0,
        "mosquito_roll10": 365.2,
        "dry_roll10": 2.9,
        "heat_trend": 128.0,
        "muggy_trend": 114.1,
        "rain_trend": 26.8,
        "snow_trend": 0.0,
        "mosquito_trend": 358.9,
        "dry_trend": 3.2,
        "springFrost": 0,
        "fallFrost": 0
      },
      "2042": {
        "heat": 129,
        "muggy": 130,
        "rain": 28,
        "snow": 0,
        "mosquito": 351,
        "dry": 4,
        "heat_roll5": 129.6,
        "muggy_roll5": 118.2,
        "rain_roll5": 20.8,
        "snow_roll5": 0.0,
        "mosquito_roll5": 353.0,
        "dry_roll5": 4.4,
        "heat_roll10": 115.9,
        "muggy_roll10": 95.8,
        "rain_roll10": 25.2,
        "snow_roll10": 0.0,
        "mosquito_roll10": 362.4,
        "dry_roll10": 3.2,
        "heat_trend": 129.9,
        "muggy_trend": 118.5,
        "rain_trend": 26.5,
        "snow_trend": 0.0,
        "mosquito_trend": 357.6,
        "dry_trend": 3.3,
        "springFrost": 0,
        "fallFrost": 0
      },
      "2043": {
        "heat": 75,
        "muggy": 140,
        "rain": 18,
        "snow": 0,
        "mosquito": 303,
        "dry": 5,
        "heat_roll5": 117.4,
        "muggy_roll5": 126.0,
        "rain_roll5": 22.0,
        "snow_roll5": 0.0,
        "mosquito_roll5": 342.0,
        "dry_roll5": 4.6,
        "heat_roll10": 115.1,
        "muggy_roll10": 104.0,
        "rain_roll10": 25.0,
        "snow_roll10": 0.0,
        "mosquito_roll10": 355.1,
        "dry_roll10": 3.5,
        "heat_trend": 131.7,
        "muggy_trend": 123.0,
        "rain_trend": 26.1,
        "snow_trend": 0.0,
        "mosquito_trend": 355.9,
        "dry_trend": 3.4,
        "springFrost": 0,
        "fallFrost": 0
      },
      "2044": {
        "heat": 116,
        "muggy": 156,
        "rain": 14,
        "snow": 0,
        "mosquito": 315,
        "dry": 8,
        "heat_roll5": 118.4,
        "muggy_roll5": 140.6,
        "rain_roll5": 18.8,
        "snow_roll5": 0.0,
        "mosquito_roll5": 333.2,
        "dry_roll5": 5.4,
        "heat_roll10": 117.7,
        "muggy_roll10": 112.4,
        "rain_roll10": 23.0,
        "snow_roll10": 0.0,
        "mosquito_roll10": 349.0,
        "dry_roll10": 4.3,
        "heat_trend": 133.2,
        "muggy_trend": 127.6,
        "rain_trend": 25.6,
        "snow_trend": 0.0,
        "mosquito_trend": 354.0,
        "dry_trend": 3.5,
        "springFrost": 0,
        "fallFrost": 0
      },
      "2045": {
        "heat": 135,
        "muggy": 75,
        "rain": 44,
        "snow": 0,
        "mosquito": 389,
        "dry": 0,
        "heat_roll5": 122.0,
        "muggy_roll5": 130.4,
        "rain_roll5": 25.6,
        "snow_roll5": 0.0,
        "mosquito_roll5": 345.4,
        "dry_roll5": 3.8,
        "heat_roll10": 121.3,
        "muggy_roll10": 113.0,
        "rain_roll10": 25.0,
        "snow_roll10": 0.0,
        "mosquito_roll10": 352.5,
        "dry_roll10": 3.7,
        "heat_trend": 134.4,
        "muggy_trend": 132.4,
        "rain_trend": 25.1,
        "snow_trend": 0.0,
        "mosquito_trend": 351.7,
        "dry_trend": 3.7,
        "springFrost": 0,
        "fallFrost": 0
      },
      "2046": {
        "heat": 111,
        "muggy": 83,
        "rain": 28,
        "snow": 0,
        "mosquito": 336,
        "dry": 4,
        "heat_roll5": 113.2,
        "muggy_roll5": 116.8,
        "rain_roll5": 26.4,
        "snow_roll5": 0.0,
        "mosquito_roll5": 338.8,
        "dry_roll5": 4.2,
        "heat_roll10": 121.8,
        "muggy_roll10": 114.8,
        "rain_roll10": 24.0,
        "snow_roll10": 0.0,
        "mosquito_roll10": 348.6,
        "dry_roll10": 4.1,
        "heat_trend": 135.5,
        "muggy_trend": 137.3,
        "rain_trend": 24.5,
        "snow_trend": 0.0,
        "mosquito_trend": 349.2,
        "dry_trend": 3.9,
        "springFrost": 0,
        "fallFrost": 0
      },
      "2047": {
        "heat": 156,
        "muggy": 163,
        "rain": 38,
        "snow": 0,
        "mosquito": 368,
        "dry": 4,
        "heat_roll5": 118.6,
        "muggy_roll5": 123.4,
        "rain_roll5": 28.4,
        "snow_roll5": 0.0,
        "mosquito_roll5": 342.2,
        "dry_roll5": 4.2,
        "heat_roll10": 124.1,
        "muggy_roll10": 120.8,
        "rain_roll10": 24.6,
        "snow_roll10": 0.0,
        "mosquito_roll10": 347.6,
        "dry_roll10": 4.3,
        "heat_trend": 136.2,
        "muggy_trend": 142.3,
        "rain_trend": 23.9,
        "snow_trend": 0.0,
        "mosquito_trend": 346.4,
        "dry_trend": 4.2,
        "springFrost": 0,
        "fallFrost": 0
      },
      "2048": {
        "heat": 184,
        "muggy": 156,
        "rain": 20,
        "snow": 0,
        "mosquito": 374,
        "dry": 0,
        "heat_roll5": 140.4,
        "muggy_roll5": 126.6,
        "rain_roll5": 28.8,
        "snow_roll5": 0.0,
        "mosquito_roll5": 356.4,
        "dry_roll5": 3.2,
        "heat_roll10": 128.9,
        "muggy_roll10": 126.3,
        "rain_roll10": 25.4,
        "snow_roll10": 0.0,
        "mosquito_roll10": 349.2,
        "dry_roll10": 3.9,
        "heat_trend": 136.8,
        "muggy_trend": 147.4,
        "rain_trend": 23.1,
        "snow_trend": 0.0,
        "mosquito_trend": 343.2,
        "dry_trend": 4.4,
        "springFrost": 0,
        "fallFrost": 0
      },
      "2049": {
        "heat": 128,
        "muggy": 157,
        "rain": 26,
        "snow": 0,
        "mosquito": 341,
        "dry": 5,
        "heat_roll5": 142.8,
        "muggy_roll5": 126.8,
        "rain_roll5": 31.2,
        "snow_roll5": 0.0,
        "mosquito_roll5": 361.6,
        "dry_roll5": 2.6,
        "heat_roll10": 130.6,
        "muggy_roll10": 133.7,
        "rain_roll10": 25.0,
        "snow_roll10": 0.0,
        "mosquito_roll10": 347.4,
        "dry_roll10": 4.0,
        "heat_trend": 137.1,
        "muggy_trend": 152.7,
        "rain_trend": 22.3,
        "snow_trend": 0.0,
        "mosquito_trend": 339.8,
        "dry_trend": 4.8,
        "springFrost": 0,
        "fallFrost": 0
      },
      "2050": {
        "heat": 138,
        "muggy": 170,
        "rain": 12,
        "snow": 0,
        "mosquito": 329,
        "dry": 7,
        "heat_roll5": 143.4,
        "muggy_roll5": 145.8,
        "rain_roll5": 24.8,
        "snow_roll5": 0.0,
        "mosquito_roll5": 349.6,
        "dry_roll5": 4.0,
        "heat_roll10": 132.7,
        "muggy_roll10": 138.1,
        "rain_roll10": 25.2,
        "snow_roll10": 0.0,
        "mosquito_roll10": 347.5,
        "dry_roll10": 3.9,
        "heat_trend": 137.2,
        "muggy_trend": 158.1,
        "rain_trend": 21.4,
        "snow_trend": 0.0,
        "mosquito_trend": 336.1,
        "dry_trend": 5.1,
        "springFrost": 0,
        "fallFrost": 0
      }
    }
  }
}